{
  "model_id": "TRANSFORM.Math.Examples.check_smoothMin",
  "test_id": "0120",
  "status": "active",
  "date_added": "2026-04-22T17:28:48.500246+00:00",
  "last_updated": "2026-04-22T17:28:48.500246+00:00",
  "simulation": {
    "stop_time": 20.0,
    "tolerance": 0.0001,
    "method": "Dassl",
    "number_of_intervals": 500,
    "output_interval": null
  },
  "statistics": {
    "timing": {
      "frontend": 0.17039490000000002,
      "backend": 0.02235049999999994,
      "simcode": 0.0037365000000000002,
      "templates": 0.1180694,
      "compile": 2.3335735,
      "simulation": 0.044555000000000004,
      "total": 2.6951641,
      "translation_wall": 2.65,
      "sim_wall": 0.04,
      "other_wall": 101.0,
      "total_wall": 103.69
    }
  },
  "n_vars": 4,
  "time": [
    0.0,
    0.04,
    0.08,
    0.12,
    0.16,
    0.2,
    0.24,
    0.28,
    0.32,
    0.36,
    0.4,
    0.44,
    0.48,
    0.52,
    0.56,
    0.6,
    0.64,
    0.68,
    0.72,
    0.76,
    0.8,
    0.84,
    0.88,
    0.92,
    0.96,
    1.0,
    1.04,
    1.08,
    1.12,
    1.16,
    1.2,
    1.24,
    1.28,
    1.32,
    1.36,
    1.4,
    1.44,
    1.48,
    1.52,
    1.56,
    1.6,
    1.64,
    1.68,
    1.72,
    1.76,
    1.8,
    1.84,
    1.88,
    1.92,
    1.96,
    2.0,
    2.04,
    2.08,
    2.12,
    2.16,
    2.2,
    2.24,
    2.28,
    2.32,
    2.36,
    2.4,
    2.44,
    2.48,
    2.52,
    2.56,
    2.6,
    2.64,
    2.68,
    2.72,
    2.76,
    2.8,
    2.84,
    2.88,
    2.92,
    2.96,
    3.0,
    3.04,
    3.08,
    3.12,
    3.16,
    3.2,
    3.24,
    3.28,
    3.32,
    3.36,
    3.4,
    3.44,
    3.48,
    3.52,
    3.56,
    3.6,
    3.64,
    3.68,
    3.72,
    3.76,
    3.8,
    3.84,
    3.88,
    3.92,
    3.96,
    4.0,
    4.04,
    4.08,
    4.12,
    4.16,
    4.2,
    4.24,
    4.28,
    4.32,
    4.36,
    4.4,
    4.44,
    4.48,
    4.52,
    4.56,
    4.6,
    4.64,
    4.68,
    4.72,
    4.76,
    4.8,
    4.84,
    4.88,
    4.92,
    4.96,
    5.0,
    5.04,
    5.08,
    5.12,
    5.16,
    5.2,
    5.24,
    5.28,
    5.32,
    5.36,
    5.4,
    5.44,
    5.48,
    5.52,
    5.56,
    5.6,
    5.64,
    5.68,
    5.72,
    5.76,
    5.8,
    5.84,
    5.88,
    5.92,
    5.96,
    6.0,
    6.04,
    6.08,
    6.12,
    6.16,
    6.2,
    6.24,
    6.28,
    6.32,
    6.36,
    6.4,
    6.44,
    6.48,
    6.52,
    6.56,
    6.6,
    6.64,
    6.68,
    6.72,
    6.76,
    6.8,
    6.84,
    6.88,
    6.92,
    6.96,
    7.0,
    7.04,
    7.08,
    7.12,
    7.16,
    7.2,
    7.24,
    7.28,
    7.32,
    7.36,
    7.4,
    7.44,
    7.48,
    7.52,
    7.56,
    7.6,
    7.64,
    7.68,
    7.72,
    7.76,
    7.8,
    7.84,
    7.88,
    7.92,
    7.96,
    8.0,
    8.04,
    8.08,
    8.12,
    8.16,
    8.2,
    8.24,
    8.28,
    8.32,
    8.36,
    8.4,
    8.44,
    8.48,
    8.52,
    8.56,
    8.6,
    8.64,
    8.68,
    8.72,
    8.76,
    8.8,
    8.84,
    8.88,
    8.92,
    8.96,
    9.0,
    9.04,
    9.08,
    9.12,
    9.16,
    9.2,
    9.24,
    9.28,
    9.32,
    9.36,
    9.4,
    9.44,
    9.48,
    9.52,
    9.56,
    9.6,
    9.64,
    9.68,
    9.72,
    9.76,
    9.8,
    9.84,
    9.88,
    9.92,
    9.96,
    10.0,
    10.04,
    10.08,
    10.12,
    10.16,
    10.2,
    10.24,
    10.28,
    10.32,
    10.36,
    10.4,
    10.44,
    10.48,
    10.52,
    10.56,
    10.6,
    10.64,
    10.68,
    10.72,
    10.76,
    10.8,
    10.84,
    10.88,
    10.92,
    10.96,
    11.0,
    11.04,
    11.08,
    11.12,
    11.16,
    11.2,
    11.24,
    11.28,
    11.32,
    11.36,
    11.4,
    11.44,
    11.48,
    11.52,
    11.56,
    11.6,
    11.64,
    11.68,
    11.72,
    11.76,
    11.8,
    11.84,
    11.88,
    11.92,
    11.96,
    12.0,
    12.04,
    12.08,
    12.12,
    12.16,
    12.2,
    12.24,
    12.28,
    12.32,
    12.36,
    12.4,
    12.44,
    12.48,
    12.52,
    12.56,
    12.6,
    12.64,
    12.68,
    12.72,
    12.76,
    12.8,
    12.84,
    12.88,
    12.92,
    12.96,
    13.0,
    13.04,
    13.08,
    13.12,
    13.16,
    13.2,
    13.24,
    13.28,
    13.32,
    13.36,
    13.4,
    13.44,
    13.48,
    13.52,
    13.56,
    13.6,
    13.64,
    13.68,
    13.72,
    13.76,
    13.8,
    13.84,
    13.88,
    13.92,
    13.96,
    14.0,
    14.04,
    14.08,
    14.12,
    14.16,
    14.2,
    14.24,
    14.28,
    14.32,
    14.36,
    14.4,
    14.44,
    14.48,
    14.52,
    14.56,
    14.6,
    14.64,
    14.68,
    14.72,
    14.76,
    14.8,
    14.84,
    14.88,
    14.92,
    14.96,
    15.0,
    15.04,
    15.08,
    15.12,
    15.16,
    15.2,
    15.24,
    15.28,
    15.32,
    15.36,
    15.4,
    15.44,
    15.48,
    15.52,
    15.56,
    15.6,
    15.64,
    15.68,
    15.72,
    15.76,
    15.8,
    15.84,
    15.88,
    15.92,
    15.96,
    16.0,
    16.04,
    16.08,
    16.12,
    16.16,
    16.2,
    16.24,
    16.28,
    16.32,
    16.36,
    16.4,
    16.44,
    16.48,
    16.52,
    16.56,
    16.6,
    16.64,
    16.68,
    16.72,
    16.76,
    16.8,
    16.84,
    16.88,
    16.92,
    16.96,
    17.0,
    17.04,
    17.08,
    17.12,
    17.16,
    17.2,
    17.24,
    17.28,
    17.32,
    17.36,
    17.4,
    17.44,
    17.48,
    17.52,
    17.56,
    17.6,
    17.64,
    17.68,
    17.72,
    17.76,
    17.8,
    17.84,
    17.88,
    17.92,
    17.96,
    18.0,
    18.04,
    18.08,
    18.12,
    18.16,
    18.2,
    18.24,
    18.28,
    18.32,
    18.36,
    18.4,
    18.44,
    18.48,
    18.52,
    18.56,
    18.6,
    18.64,
    18.68,
    18.72,
    18.76,
    18.8,
    18.84,
    18.88,
    18.92,
    18.96,
    19.0,
    19.04,
    19.08,
    19.12,
    19.16,
    19.2,
    19.24,
    19.28,
    19.32,
    19.36,
    19.4,
    19.44,
    19.48,
    19.52,
    19.56,
    19.6,
    19.64,
    19.68,
    19.72,
    19.76,
    19.8,
    19.84,
    19.88,
    19.92,
    19.96,
    20.0,
    20.0
  ],
  "variables": [
    {
      "index": 1,
      "name": "y[1]",
      "values": [
        0.0,
        0.04,
        0.08,
        0.12,
        0.16,
        0.2,
        0.24,
        0.28,
        0.32,
        0.36,
        0.4,
        0.44,
        0.48,
        0.52,
        0.56,
        0.6,
        0.64,
        0.68,
        0.72,
        0.76,
        0.8,
        0.84,
        0.88,
        0.92,
        0.96,
        1.0,
        1.04,
        1.08,
        1.12,
        1.16,
        1.2,
        1.24,
        1.28,
        1.32,
        1.36,
        1.4,
        1.44,
        1.48,
        1.52,
        1.56,
        1.6,
        1.64,
        1.68,
        1.72,
        1.76,
        1.8,
        1.84,
        1.88,
        1.92,
        1.96,
        2.0,
        2.04,
        2.08,
        2.12,
        2.16,
        2.2,
        2.24,
        2.28,
        2.32,
        2.36,
        2.4,
        2.44,
        2.48,
        2.52,
        2.56,
        2.6,
        2.64,
        2.68,
        2.72,
        2.76,
        2.8,
        2.84,
        2.88,
        2.92,
        2.96,
        3.0,
        3.04,
        3.08,
        3.12,
        3.16,
        3.2,
        3.24,
        3.28,
        3.32,
        3.36,
        3.4,
        3.44,
        3.48,
        3.52,
        3.56,
        3.6,
        3.64,
        3.68,
        3.72,
        3.76,
        3.8,
        3.84,
        3.88,
        3.92,
        3.96,
        4.0,
        4.04,
        4.08,
        4.12,
        4.16,
        4.2,
        4.24,
        4.28,
        4.32,
        4.36,
        4.4,
        4.44,
        4.48,
        4.52,
        4.56,
        4.6,
        4.64,
        4.68,
        4.72,
        4.76,
        4.8,
        4.84,
        4.88,
        4.92,
        4.96,
        5.0,
        5.04,
        5.08,
        5.12,
        5.16,
        5.20000000000007,
        5.24000000001512,
        5.28000000066853,
        5.32000001146458,
        5.360000104539,
        5.40000061258753,
        5.4400026024997,
        5.48000868669377,
        5.52002408388882,
        5.56005771231402,
        5.60012306589785,
        5.64023868575604,
        5.6804281465037,
        5.72071957982692,
        5.76114482846965,
        5.80173835647861,
        5.84253604340297,
        5.88357397265733,
        5.9248872979418,
        5.96650924396657,
        6.00847027310763,
        6.05079742994916,
        6.09351386129283,
        6.13663849961964,
        6.18018589229389,
        6.22416615605499,
        6.26858503569223,
        6.31344404653562,
        6.35874068197887,
        6.40446866928412,
        6.45061825912566,
        6.4971765365318,
        6.54412774296742,
        6.59145360120215,
        6.63913363630091,
        6.68714548754794,
        6.73546520737915,
        6.78406754446428,
        6.8329262089701,
        6.88201411876735,
        6.9313036259385,
        6.98076672341929,
        7.0303752319815,
        7.08010096805413,
        7.12991589309801,
        7.1797922454076,
        7.22970265532359,
        7.27962024490985,
        7.32951871318601,
        7.37937240801919,
        7.42915638576974,
        7.47884645976247,
        7.52841923861855,
        7.57785215543908,
        7.62712348878045,
        7.67621237630712,
        7.72509882195027,
        7.77376369734303,
        7.82218873824528,
        7.87035653661419,
        7.91825052892171,
        7.96585498126736,
        8.01315497178403,
        8.06013637078723,
        8.10678581907296,
        8.15309070472774,
        8.19903913877545,
        8.24461992994921,
        8.28982255884388,
        8.33463715167375,
        8.37905445383251,
        8.4230658034269,
        8.4666631049328,
        8.50983880310114,
        8.55258585722289,
        8.59489771584482,
        8.63676829201327,
        8.6781919391091,
        8.71916342732546,
        8.75967792082916,
        8.79973095563707,
        8.83931841823083,
        8.87843652492591,
        8.91708180200475,
        8.95525106661831,
        8.9929414084558,
        9.03015017217818,
        9.06687494060774,
        9.10311351866333,
        9.13886391802836,
        9.17412434253664,
        9.20889317426005,
        9.24316896028022,
        9.27695040012608,
        9.31023633385811,
        9.34302573077989,
        9.37531767875739,
        9.40711137412613,
        9.43840611216698,
        9.46920127813101,
        9.49949633879459,
        9.52929083452631,
        9.55858437184765,
        9.58737661647023,
        9.61566728679281,
        9.64345614784227,
        9.6707430056432,
        9.69752770200183,
        9.72381010969056,
        9.74959012802051,
        9.77486767878995,
        9.79964270259772,
        9.82391515551137,
        9.8476850060807,
        9.87095223268836,
        9.89371682122983,
        9.91597876311623,
        9.93773805359415,
        9.9589946903776,
        9.97974867258813,
        10.0,
        10.0197486725881,
        10.0389946903776,
        10.0577380535942,
        10.0759787631162,
        10.0937168212298,
        10.1109522326884,
        10.1276850060807,
        10.1439151555114,
        10.1596427025977,
        10.17486767879,
        10.1895901280205,
        10.2038101096906,
        10.2175277020018,
        10.2307430056432,
        10.2434561478423,
        10.2556672867928,
        10.2673766164702,
        10.2785843718477,
        10.2892908345263,
        10.2994963387946,
        10.309201278131,
        10.318406112167,
        10.3271113741261,
        10.3353176787574,
        10.3430257307799,
        10.3502363338581,
        10.3569504001261,
        10.3631689602802,
        10.36889317426,
        10.3741243425366,
        10.3788639180284,
        10.3831135186633,
        10.3868749406077,
        10.3901501721782,
        10.3929414084558,
        10.3952510666183,
        10.3970818020047,
        10.3984365249259,
        10.3993184182308,
        10.3997309556371,
        10.3996779208292,
        10.3991634273255,
        10.3981919391091,
        10.3967682920133,
        10.3948977158448,
        10.3925858572229,
        10.3898388031011,
        10.3866631049328,
        10.3830658034269,
        10.3790544538325,
        10.3746371516737,
        10.3698225588439,
        10.3646199299492,
        10.3590391387755,
        10.3530907047277,
        10.346785819073,
        10.3401363707872,
        10.333154971784,
        10.3258549812674,
        10.3182505289217,
        10.3103565366142,
        10.3021887382453,
        10.293763697343,
        10.2850988219503,
        10.2762123763071,
        10.2671234887804,
        10.2578521554391,
        10.2484192386186,
        10.2388464597625,
        10.2291563857697,
        10.2193724080192,
        10.209518713186,
        10.1996202449098,
        10.1897026553236,
        10.1797922454076,
        10.169915893098,
        10.1601009680541,
        10.1503752319815,
        10.1407667234193,
        10.1313036259385,
        10.1220141187673,
        10.1129262089701,
        10.1040675444643,
        10.0954652073791,
        10.0871454875479,
        10.0791336363009,
        10.0714536012022,
        10.0641277429674,
        10.0571765365318,
        10.0506182591257,
        10.0444686692841,
        10.0387406819789,
        10.0334440465356,
        10.0285850356922,
        10.024166156055,
        10.0201858922939,
        10.0166384996196,
        10.0135138612928,
        10.0107974299492,
        10.0084702731076,
        10.0065092439666,
        10.0048872979418,
        10.0035739726573,
        10.002536043403,
        10.0017383564786,
        10.0011448284696,
        10.0007195798269,
        10.0004281465037,
        10.000238685756,
        10.0001230658978,
        10.000057712314,
        10.0000240838888,
        10.0000086866938,
        10.0000026024997,
        10.0000006125875,
        10.000000104539,
        10.0000000114646,
        10.0000000006685,
        10.0000000000151,
        10.0000000000001,
        10.0,
        10.0,
        10.0,
        10.0,
        10.0,
        10.0,
        10.0,
        10.0,
        10.0,
        10.0,
        10.0,
        10.0,
        10.0,
        10.0,
        10.0,
        10.0,
        10.0,
        10.0,
        10.0,
        10.0,
        10.0,
        10.0,
        10.0,
        10.0,
        10.0,
        10.0,
        10.0,
        10.0,
        10.0,
        10.0,
        10.0,
        10.0,
        10.0,
        10.0,
        10.0,
        10.0,
        10.0,
        10.0,
        10.0,
        10.0,
        10.0,
        10.0,
        10.0,
        10.0,
        10.0,
        10.0,
        10.0,
        10.0,
        10.0,
        10.0,
        10.0,
        10.0,
        10.0,
        10.0,
        10.0,
        10.0,
        10.0,
        10.0,
        10.0,
        10.0,
        10.0,
        10.0,
        10.0,
        10.0,
        10.0,
        10.0,
        10.0,
        10.0,
        10.0,
        10.0,
        10.0,
        10.0,
        10.0,
        10.0,
        10.0,
        10.0,
        10.0,
        10.0,
        10.0,
        10.0,
        10.0,
        10.0,
        10.0,
        10.0,
        10.0,
        10.0,
        10.0,
        10.0,
        10.0,
        10.0,
        10.0,
        10.0,
        10.0,
        10.0,
        10.0,
        10.0,
        10.0,
        10.0,
        10.0,
        10.0,
        10.0,
        10.0,
        10.0,
        10.0,
        10.0,
        10.0,
        10.0,
        10.0,
        10.0,
        10.0,
        10.0,
        10.0,
        10.0,
        10.0,
        10.0,
        10.0,
        10.0,
        10.0,
        10.0,
        10.0,
        10.0,
        10.0,
        10.0,
        10.0,
        10.0,
        10.0,
        10.0,
        10.0,
        10.0,
        10.0,
        10.0
      ]
    },
    {
      "index": 2,
      "name": "y[2]",
      "values": [
        -0.000419257966119578,
        0.0395671111711426,
        0.0795530372227208,
        0.119538505790878,
        0.159523502010381,
        0.199508010533339,
        0.239492015513563,
        0.279475500590407,
        0.319458448872099,
        0.359440842918525,
        0.39942266472346,
        0.439403895696229,
        0.479384516642766,
        0.519364507746076,
        0.559343848546053,
        0.599322517918654,
        0.639300494054402,
        0.679277754436193,
        0.719254275816388,
        0.759230034193171,
        0.799205004786136,
        0.839179162011102,
        0.879152479454104,
        0.919124929844554,
        0.959096485027536,
        0.999067115935215,
        1.03903679255732,
        1.07900548391068,
        1.11897315800778,
        1.15893978182433,
        1.19890532126574,
        1.2388697411326,
        1.27883300508495,
        1.3187950756055,
        1.35875591396162,
        1.39871548016615,
        1.43867373293686,
        1.47863062965479,
        1.51858612632106,
        1.55854017751243,
        1.59849273633542,
        1.63844375437892,
        1.67839318166533,
        1.71834096660013,
        1.75828705591984,
        1.79823139463834,
        1.83817392599145,
        1.87811459137979,
        1.91805333030978,
        1.95799008033281,
        1.99792477698244,
        2.03785735370968,
        2.0777877418161,
        2.11771587038496,
        2.15764166621008,
        2.19756505372246,
        2.23748595491465,
        2.27740428926269,
        2.31731997364556,
        2.35723292226221,
        2.39714304654584,
        2.43705025507562,
        2.47695445348556,
        2.51685554437055,
        2.5567534271895,
        2.59664799816539,
        2.63653915018228,
        2.67642677267905,
        2.71631075153988,
        2.75619096898131,
        2.7960673034358,
        2.83593962943171,
        2.87580781746958,
        2.91567173389452,
        2.95553124076481,
        2.99538619571632,
        3.03523645182287,
        3.07508185745233,
        3.1149222561182,
        3.15475748632687,
        3.19458738142004,
        3.2344117694125,
        3.27423047282496,
        3.31404330851181,
        3.35385008748374,
        3.39365061472502,
        3.43344468900533,
        3.47323210268592,
        3.51301264152009,
        3.5527860844477,
        3.5925522033836,
        3.63231076299986,
        3.6720615205016,
        3.71180422539625,
        3.75153861925609,
        3.79126443547395,
        3.83098139901175,
        3.87068922614188,
        3.91038762418118,
        3.95007629121727,
        3.98975491582717,
        4.02942317678791,
        4.06908074277911,
        4.10872727207715,
        4.14836241224089,
        4.18798579978871,
        4.22759705986663,
        4.26719580590749,
        4.30678163928075,
        4.34635414893298,
        4.38591291101868,
        4.42545748852134,
        4.46498743086452,
        4.50450227351279,
        4.54400153756234,
        4.58348472932109,
        4.62295133987817,
        4.66240084466257,
        4.70183270299074,
        4.74124635760321,
        4.78064123418979,
        4.82001674090346,
        4.85937226786268,
        4.8987071866421,
        4.93802084975147,
        4.97731259010274,
        5.01658172046523,
        5.05582753290886,
        5.09504929823526,
        5.13424626539695,
        5.17341766090429,
        5.21256268822058,
        5.25168052714492,
        5.2907703331833,
        5.32983123690766,
        5.36886234330329,
        5.40786273110454,
        5.44683145211913,
        5.48576753054115,
        5.52466996225318,
        5.56353771411763,
        5.60236972325768,
        5.64116489632832,
        5.67992210877772,
        5.71864020409953,
        5.75731799307663,
        5.79595425301684,
        5.83454772698128,
        5.87309712300612,
        5.91160111331842,
        5.95005833354696,
        5.98846738192893,
        6.02682681851351,
        6.06513516436345,
        6.10339090075564,
        6.14159246838216,
        6.17973826655296,
        6.21782665240166,
        6.25585594009604,
        6.29382440005484,
        6.3317302581725,
        6.36957169505392,
        6.40734684526099,
        6.44505379657307,
        6.48269058926361,
        6.52025521539524,
        6.55774561813576,
        6.59515969109758,
        6.63249527770342,
        6.66975017058095,
        6.70692211098946,
        6.74400878828164,
        6.7810078394036,
        6.81791684843665,
        6.85473334618422,
        6.89145480980756,
        6.92807866251401,
        6.96460227330165,
        7.00102295676441,
        7.03733797296158,
        7.07354452735616,
        7.10963977082607,
        7.14562079975289,
        7.18148465619239,
        7.2172283281315,
        7.2528487498363,
        7.28834280229561,
        7.32370731376489,
        7.35893906041513,
        7.39403476709127,
        7.42899110818495,
        7.46380470862599,
        7.49847214499714,
        7.53298994677654,
        7.56735459771206,
        7.60156253733166,
        7.63561016259364,
        7.66949382968047,
        7.70320985593968,
        7.73675452197485,
        7.77012407388958,
        7.80331472568688,
        7.83632266182612,
        7.86914403993893,
        7.90177499370558,
        7.93421163589209,
        7.96645006154856,
        7.99848635136788,
        8.03031657520401,
        8.06193679574803,
        8.09334307235935,
        8.12453146504925,
        8.15549803861257,
        8.18623886690316,
        8.21675003724744,
        8.24702765499003,
        8.27706784816425,
        8.30686677227965,
        8.33642061521787,
        8.36572560222728,
        8.39477800100602,
        8.42357412686223,
        8.45211034793958,
        8.48038309049526,
        8.50838884421706,
        8.53612416756528,
        8.56358569312479,
        8.59077013295174,
        8.61767428389896,
        8.64429503290388,
        8.67062936222183,
        8.69667435458801,
        8.72242719829044,
        8.74788519213674,
        8.77304575029698,
        8.79790640700532,
        8.82246482110305,
        8.84671878040602,
        8.8706662058797,
        8.89430515560585,
        8.91763382852491,
        8.94065056793925,
        8.9633538647632,
        8.98574236050627,
        9.00781484997745,
        9.02957028369908,
        9.05100777002023,
        9.07212657692057,
        9.09292613349692,
        9.11340603112627,
        9.13356602430007,
        9.15340603112627,
        9.17292613349692,
        9.19212657692057,
        9.21100777002023,
        9.22957028369908,
        9.24781484997745,
        9.26574236050627,
        9.2833538647632,
        9.30065056793925,
        9.31763382852491,
        9.33430515560585,
        9.3506662058797,
        9.36671878040602,
        9.38246482110305,
        9.39790640700532,
        9.41304575029698,
        9.42788519213674,
        9.44242719829044,
        9.45667435458801,
        9.47062936222183,
        9.48429503290388,
        9.49767428389896,
        9.51077013295174,
        9.5235856931248,
        9.53612416756528,
        9.54838884421705,
        9.56038309049526,
        9.57211034793958,
        9.58357412686223,
        9.59477800100601,
        9.60572560222728,
        9.61642061521787,
        9.62686677227965,
        9.63706784816425,
        9.64702765499003,
        9.65675003724744,
        9.66623886690316,
        9.67549803861257,
        9.68453146504925,
        9.69334307235935,
        9.70193679574803,
        9.71031657520401,
        9.71848635136788,
        9.72645006154856,
        9.7342116358921,
        9.74177499370558,
        9.74914403993893,
        9.75632266182612,
        9.76331472568688,
        9.77012407388958,
        9.77675452197485,
        9.78320985593968,
        9.78949382968047,
        9.79561016259364,
        9.80156253733166,
        9.80735459771206,
        9.81298994677654,
        9.81847214499714,
        9.82380470862599,
        9.82899110818495,
        9.83403476709127,
        9.83893906041513,
        9.84370731376489,
        9.84834280229561,
        9.8528487498363,
        9.8572283281315,
        9.86148465619239,
        9.86562079975289,
        9.86963977082607,
        9.87354452735616,
        9.87733797296158,
        9.88102295676441,
        9.88460227330165,
        9.88807866251401,
        9.89145480980756,
        9.89473334618422,
        9.89791684843665,
        9.9010078394036,
        9.90400878828164,
        9.90692211098946,
        9.90975017058095,
        9.91249527770342,
        9.91515969109758,
        9.91774561813576,
        9.92025521539524,
        9.92269058926361,
        9.92505379657307,
        9.92734684526099,
        9.92957169505392,
        9.9317302581725,
        9.93382440005484,
        9.93585594009604,
        9.93782665240166,
        9.93973826655296,
        9.94159246838216,
        9.94339090075564,
        9.94513516436345,
        9.94682681851351,
        9.94846738192893,
        9.95005833354696,
        9.95160111331843,
        9.95309712300612,
        9.95454772698128,
        9.95595425301684,
        9.95731799307663,
        9.95864020409953,
        9.95992210877772,
        9.96116489632832,
        9.96236972325768,
        9.96353771411763,
        9.96466996225318,
        9.96576753054115,
        9.96683145211913,
        9.96786273110454,
        9.96886234330329,
        9.96983123690766,
        9.9707703331833,
        9.97168052714492,
        9.97256268822058,
        9.97341766090429,
        9.97424626539695,
        9.97504929823526,
        9.97582753290886,
        9.97658172046523,
        9.97731259010274,
        9.97802084975147,
        9.9787071866421,
        9.97937226786268,
        9.98001674090346,
        9.98064123418979,
        9.98124635760321,
        9.98183270299074,
        9.98240084466257,
        9.98295133987818,
        9.98348472932109,
        9.98400153756234,
        9.98450227351279,
        9.98498743086452,
        9.98545748852134,
        9.98591291101868,
        9.98635414893298,
        9.98678163928075,
        9.98719580590749,
        9.98759705986663,
        9.98798579978871,
        9.98836241224089,
        9.98872727207715,
        9.98908074277911,
        9.98942317678791,
        9.98975491582716,
        9.99007629121727,
        9.99038762418119,
        9.99068922614188,
        9.99098139901175,
        9.99126443547395,
        9.9915386192561,
        9.99180422539625,
        9.9920615205016,
        9.99231076299986,
        9.9925522033836,
        9.9927860844477,
        9.99301264152009,
        9.99323210268592,
        9.99344468900533,
        9.99365061472502,
        9.99385008748374,
        9.99404330851181,
        9.99423047282496,
        9.9944117694125,
        9.99458738142004,
        9.99475748632687,
        9.9949222561182,
        9.99508185745233,
        9.99523645182287,
        9.99538619571632,
        9.99553124076481,
        9.99567173389452,
        9.99580781746958,
        9.99593962943171,
        9.9960673034358,
        9.99619096898131,
        9.99631075153988,
        9.99642677267905,
        9.99653915018228,
        9.99664799816539,
        9.9967534271895,
        9.99685554437055,
        9.99695445348556,
        9.99705025507562,
        9.99714304654584,
        9.99723292226221,
        9.99731997364556,
        9.99740428926269,
        9.99748595491465,
        9.99756505372246,
        9.99764166621008,
        9.99771587038496,
        9.9977877418161,
        9.99785735370968,
        9.99792477698244,
        9.99799008033281,
        9.99805333030978,
        9.99811459137979,
        9.99817392599145,
        9.99823139463834,
        9.99828705591984,
        9.99834096660013,
        9.99839318166533,
        9.99844375437892,
        9.99849273633542,
        9.99854017751243,
        9.99858612632106,
        9.99863062965479,
        9.99867373293686,
        9.99871548016615,
        9.99875591396162,
        9.9987950756055,
        9.99883300508495,
        9.9988697411326,
        9.99890532126574,
        9.99893978182433,
        9.99897315800778,
        9.99900548391068,
        9.99903679255732,
        9.99906711593522,
        9.99909648502754,
        9.99912492984455,
        9.9991524794541,
        9.9991791620111,
        9.99920500478614,
        9.99923003419317,
        9.99925427581639,
        9.99927775443619,
        9.9993004940544,
        9.99932251791865,
        9.99934384854605,
        9.99936450774608,
        9.99938451664277,
        9.99940389569623,
        9.99942266472346,
        9.99944084291852,
        9.9994584488721,
        9.99947550059041,
        9.99949201551356,
        9.99950801053334,
        9.99952350201038,
        9.99953850579088,
        9.99955303722272,
        9.99956711117114,
        9.99958074203388,
        9.99958074203388
      ]
    },
    {
      "index": 3,
      "name": "y[3]",
      "values": [
        0.0,
        0.04,
        0.08,
        0.12,
        0.16,
        0.2,
        0.24,
        0.28,
        0.32,
        0.36,
        0.4,
        0.44,
        0.48,
        0.52,
        0.56,
        0.6,
        0.64,
        0.68,
        0.72,
        0.76,
        0.8,
        0.84,
        0.88,
        0.92,
        0.96,
        1.0,
        1.04,
        1.08,
        1.12,
        1.16,
        1.2,
        1.24,
        1.28,
        1.32,
        1.36,
        1.4,
        1.44,
        1.48,
        1.52,
        1.56,
        1.6,
        1.64,
        1.68,
        1.72,
        1.76,
        1.8,
        1.84,
        1.88,
        1.92,
        1.96,
        2.0,
        2.04,
        2.08,
        2.12,
        2.16,
        2.2,
        2.24,
        2.28,
        2.32,
        2.36,
        2.4,
        2.44,
        2.48,
        2.52,
        2.56,
        2.6,
        2.64,
        2.68,
        2.72,
        2.76,
        2.8,
        2.84,
        2.88,
        2.92,
        2.96,
        3.0,
        3.04,
        3.08,
        3.12,
        3.16,
        3.2,
        3.24,
        3.28,
        3.32,
        3.36,
        3.4,
        3.44,
        3.48,
        3.52,
        3.56,
        3.6,
        3.64,
        3.68,
        3.72,
        3.76,
        3.8,
        3.84,
        3.88,
        3.92,
        3.96,
        4.0,
        4.04,
        4.08,
        4.12,
        4.16,
        4.2,
        4.24,
        4.28,
        4.32,
        4.36,
        4.4,
        4.44,
        4.48,
        4.52,
        4.56,
        4.6,
        4.64,
        4.68,
        4.72,
        4.76,
        4.8,
        4.84,
        4.88,
        4.92,
        4.96,
        5.0,
        5.03999957333333,
        5.07999658666667,
        5.11998848,
        5.15997269333333,
        5.19994666666667,
        5.23990784,
        5.27985365333333,
        5.31978154666667,
        5.35968896,
        5.39957333333333,
        5.43943210666667,
        5.47926272,
        5.51906261333333,
        5.55882922666667,
        5.59856,
        5.63825237333333,
        5.67790378666667,
        5.71751168,
        5.75707349333333,
        5.79658666666667,
        5.83604864,
        5.87545685333333,
        5.91480874666667,
        5.95410176,
        5.99333333333333,
        6.03250090666667,
        6.07160192,
        6.11063381333333,
        6.14959402666667,
        6.18848,
        6.22728917333333,
        6.26601898666667,
        6.30466688,
        6.34323029333333,
        6.38170666666667,
        6.42009344,
        6.45838805333333,
        6.49658794666667,
        6.53469056,
        6.57269333333333,
        6.61059370666667,
        6.64838912,
        6.68607701333333,
        6.72365482666667,
        6.76112,
        6.79846997333333,
        6.83570218666667,
        6.87281408,
        6.90980309333333,
        6.94666666666667,
        6.98340224,
        7.02000725333333,
        7.05647914666667,
        7.09281536,
        7.12901333333333,
        7.16507050666667,
        7.20098432,
        7.23675221333333,
        7.27237162666667,
        7.30784,
        7.34315477333333,
        7.37831338666667,
        7.41331328,
        7.44815189333333,
        7.48282666666667,
        7.51733504,
        7.55167445333333,
        7.58584234666667,
        7.61983616,
        7.65365333333333,
        7.68729130666667,
        7.72074752,
        7.75401941333333,
        7.78710442666667,
        7.82,
        7.85270357333333,
        7.88521258666667,
        7.91752448,
        7.94963669333333,
        7.98154666666667,
        8.01325184,
        8.04474965333333,
        8.07603754666667,
        8.10711296,
        8.13797333333333,
        8.16861610666667,
        8.19903872,
        8.22923861333333,
        8.25921322666667,
        8.28896,
        8.31847637333333,
        8.34775978666667,
        8.37680768,
        8.40561749333333,
        8.43418666666667,
        8.46251264,
        8.49059285333333,
        8.51842474666667,
        8.54600576,
        8.57333333333333,
        8.60040490666667,
        8.62721792,
        8.65376981333333,
        8.68005802666667,
        8.70608,
        8.73183317333333,
        8.75731498666667,
        8.78252288,
        8.80745429333333,
        8.83210666666667,
        8.85647744,
        8.88056405333333,
        8.90436394666667,
        8.92787456,
        8.95109333333333,
        8.97401770666667,
        8.99664512,
        9.01897301333333,
        9.04099882666667,
        9.06272,
        9.08413397333333,
        9.10523818666667,
        9.12603008,
        9.14650709333333,
        9.16666666666667,
        9.18650709333333,
        9.20603008,
        9.22523818666667,
        9.24413397333333,
        9.26272,
        9.28099882666667,
        9.29897301333333,
        9.31664512,
        9.33401770666667,
        9.35109333333333,
        9.36787456,
        9.38436394666667,
        9.40056405333333,
        9.41647744,
        9.43210666666667,
        9.44745429333333,
        9.46252288,
        9.47731498666667,
        9.49183317333333,
        9.50608,
        9.52005802666667,
        9.53376981333333,
        9.54721792,
        9.56040490666667,
        9.57333333333333,
        9.58600576,
        9.59842474666667,
        9.61059285333333,
        9.62251264,
        9.63418666666667,
        9.64561749333333,
        9.65680768,
        9.66775978666667,
        9.67847637333333,
        9.68896,
        9.69921322666667,
        9.70923861333333,
        9.71903872,
        9.72861610666667,
        9.73797333333333,
        9.74711296,
        9.75603754666667,
        9.76474965333333,
        9.77325184,
        9.78154666666667,
        9.78963669333333,
        9.79752448,
        9.80521258666667,
        9.81270357333333,
        9.82,
        9.82710442666667,
        9.83401941333333,
        9.84074752,
        9.84729130666667,
        9.85365333333333,
        9.85983616,
        9.86584234666667,
        9.87167445333333,
        9.87733504,
        9.88282666666667,
        9.88815189333333,
        9.89331328,
        9.89831338666667,
        9.90315477333333,
        9.90784,
        9.91237162666667,
        9.91675221333333,
        9.92098432,
        9.92507050666667,
        9.92901333333333,
        9.93281536,
        9.93647914666667,
        9.94000725333333,
        9.94340224,
        9.94666666666667,
        9.94980309333333,
        9.95281408,
        9.95570218666667,
        9.95846997333333,
        9.96112,
        9.96365482666667,
        9.96607701333333,
        9.96838912,
        9.97059370666667,
        9.97269333333333,
        9.97469056,
        9.97658794666667,
        9.97838805333333,
        9.98009344,
        9.98170666666667,
        9.98323029333333,
        9.98466688,
        9.98601898666667,
        9.98728917333333,
        9.98848,
        9.98959402666667,
        9.99063381333333,
        9.99160192,
        9.99250090666667,
        9.99333333333333,
        9.99410176,
        9.99480874666667,
        9.99545685333333,
        9.99604864,
        9.99658666666667,
        9.99707349333333,
        9.99751168,
        9.99790378666667,
        9.99825237333333,
        9.99856,
        9.99882922666667,
        9.99906261333333,
        9.99926272,
        9.99943210666667,
        9.99957333333333,
        9.99968896,
        9.99978154666667,
        9.99985365333333,
        9.99990784,
        9.99994666666667,
        9.99997269333333,
        9.99998848,
        9.99999658666667,
        9.99999957333333,
        10.0,
        10.0,
        10.0,
        10.0,
        10.0,
        10.0,
        10.0,
        10.0,
        10.0,
        10.0,
        10.0,
        10.0,
        10.0,
        10.0,
        10.0,
        10.0,
        10.0,
        10.0,
        10.0,
        10.0,
        10.0,
        10.0,
        10.0,
        10.0,
        10.0,
        10.0,
        10.0,
        10.0,
        10.0,
        10.0,
        10.0,
        10.0,
        10.0,
        10.0,
        10.0,
        10.0,
        10.0,
        10.0,
        10.0,
        10.0,
        10.0,
        10.0,
        10.0,
        10.0,
        10.0,
        10.0,
        10.0,
        10.0,
        10.0,
        10.0,
        10.0,
        10.0,
        10.0,
        10.0,
        10.0,
        10.0,
        10.0,
        10.0,
        10.0,
        10.0,
        10.0,
        10.0,
        10.0,
        10.0,
        10.0,
        10.0,
        10.0,
        10.0,
        10.0,
        10.0,
        10.0,
        10.0,
        10.0,
        10.0,
        10.0,
        10.0,
        10.0,
        10.0,
        10.0,
        10.0,
        10.0,
        10.0,
        10.0,
        10.0,
        10.0,
        10.0,
        10.0,
        10.0,
        10.0,
        10.0,
        10.0,
        10.0,
        10.0,
        10.0,
        10.0,
        10.0,
        10.0,
        10.0,
        10.0,
        10.0,
        10.0,
        10.0,
        10.0,
        10.0,
        10.0,
        10.0,
        10.0,
        10.0,
        10.0,
        10.0,
        10.0,
        10.0,
        10.0,
        10.0,
        10.0,
        10.0,
        10.0,
        10.0,
        10.0,
        10.0,
        10.0,
        10.0,
        10.0,
        10.0,
        10.0,
        10.0,
        10.0
      ]
    },
    {
      "index": 4,
      "name": "y[4]",
      "values": [
        0.0,
        0.04,
        0.08,
        0.12,
        0.16,
        0.2,
        0.24,
        0.28,
        0.32,
        0.36,
        0.4,
        0.44,
        0.48,
        0.52,
        0.56,
        0.6,
        0.64,
        0.68,
        0.72,
        0.76,
        0.8,
        0.84,
        0.88,
        0.92,
        0.96,
        1.0,
        1.04,
        1.08,
        1.12,
        1.16,
        1.2,
        1.24,
        1.28,
        1.32,
        1.36,
        1.4,
        1.44,
        1.48,
        1.52,
        1.56,
        1.6,
        1.64,
        1.68,
        1.72,
        1.76,
        1.8,
        1.84,
        1.88,
        1.92,
        1.96,
        2.0,
        2.04,
        2.08,
        2.12,
        2.16,
        2.2,
        2.24,
        2.28,
        2.32,
        2.36,
        2.4,
        2.44,
        2.48,
        2.52,
        2.56,
        2.6,
        2.64,
        2.68,
        2.72,
        2.76,
        2.8,
        2.84,
        2.88,
        2.92,
        2.96,
        3.0,
        3.04,
        3.08,
        3.12,
        3.16,
        3.2,
        3.24,
        3.28,
        3.32,
        3.36,
        3.4,
        3.44,
        3.48,
        3.52,
        3.56,
        3.6,
        3.64,
        3.68,
        3.72,
        3.76,
        3.8,
        3.84,
        3.88,
        3.92,
        3.96,
        4.0,
        4.04,
        4.08,
        4.12,
        4.16,
        4.2,
        4.24,
        4.28,
        4.32,
        4.36,
        4.4,
        4.44,
        4.48,
        4.52,
        4.56,
        4.6,
        4.64,
        4.68,
        4.72,
        4.76,
        4.8,
        4.84,
        4.88,
        4.92,
        4.96,
        5.0,
        5.03992,
        5.07968,
        5.11928,
        5.15872,
        5.198,
        5.23712,
        5.27608,
        5.31488,
        5.35352,
        5.392,
        5.43032,
        5.46848,
        5.50648,
        5.54432,
        5.582,
        5.61952,
        5.65688,
        5.69408,
        5.73112,
        5.768,
        5.80472,
        5.84128,
        5.87768,
        5.91392,
        5.95,
        5.98592,
        6.02168,
        6.05728,
        6.09272,
        6.128,
        6.16312,
        6.19808,
        6.23288,
        6.26752,
        6.302,
        6.33632,
        6.37048,
        6.40448,
        6.43832,
        6.472,
        6.50552,
        6.53888,
        6.57208,
        6.60512,
        6.638,
        6.67072,
        6.70328,
        6.73568,
        6.76792,
        6.8,
        6.83192,
        6.86368,
        6.89528,
        6.92672,
        6.958,
        6.98912,
        7.02008,
        7.05088,
        7.08152,
        7.112,
        7.14232,
        7.17248,
        7.20248,
        7.23232,
        7.262,
        7.29152,
        7.32088,
        7.35008,
        7.37912,
        7.408,
        7.43672,
        7.46528,
        7.49368,
        7.52192,
        7.55,
        7.57792,
        7.60568,
        7.63328,
        7.66072,
        7.688,
        7.71512,
        7.74208,
        7.76888,
        7.79552,
        7.822,
        7.84832,
        7.87448,
        7.90048,
        7.92632,
        7.952,
        7.97752,
        8.00288,
        8.02808,
        8.05312,
        8.078,
        8.10272,
        8.12728,
        8.15168,
        8.17592,
        8.2,
        8.22392,
        8.24768,
        8.27128,
        8.29472,
        8.318,
        8.34112,
        8.36408,
        8.38688,
        8.40952,
        8.432,
        8.45432,
        8.47648,
        8.49848,
        8.52032,
        8.542,
        8.56352,
        8.58488,
        8.60608,
        8.62712,
        8.648,
        8.66872,
        8.68928,
        8.70968,
        8.72992,
        8.75,
        8.76992,
        8.78968,
        8.80928,
        8.82872,
        8.848,
        8.86712,
        8.88608,
        8.90488,
        8.92352,
        8.942,
        8.96032,
        8.97848,
        8.99648,
        9.01432,
        9.032,
        9.04952,
        9.06688,
        9.08408,
        9.10112,
        9.118,
        9.13472,
        9.15128,
        9.16768,
        9.18392,
        9.2,
        9.21592,
        9.23168,
        9.24728,
        9.26272,
        9.278,
        9.29312,
        9.30808,
        9.32288,
        9.33752,
        9.352,
        9.36632,
        9.38048,
        9.39448,
        9.40832,
        9.422,
        9.43552,
        9.44888,
        9.46208,
        9.47512,
        9.488,
        9.50072,
        9.51328,
        9.52568,
        9.53792,
        9.55,
        9.56192,
        9.57368,
        9.58528,
        9.59672,
        9.608,
        9.61912,
        9.63008,
        9.64088,
        9.65152,
        9.662,
        9.67232,
        9.68248,
        9.69248,
        9.70232,
        9.712,
        9.72152,
        9.73088,
        9.74008,
        9.74912,
        9.758,
        9.76672,
        9.77528,
        9.78368,
        9.79192,
        9.8,
        9.80792,
        9.81568,
        9.82328,
        9.83072,
        9.838,
        9.84512,
        9.85208,
        9.85888,
        9.86552,
        9.872,
        9.87832,
        9.88448,
        9.89048,
        9.89632,
        9.902,
        9.90752,
        9.91288,
        9.91808,
        9.92312,
        9.928,
        9.93272,
        9.93728,
        9.94168,
        9.94592,
        9.95,
        9.95392,
        9.95768,
        9.96128,
        9.96472,
        9.968,
        9.97112,
        9.97408,
        9.97688,
        9.97952,
        9.982,
        9.98432,
        9.98648,
        9.98848,
        9.99032,
        9.992,
        9.99352,
        9.99488,
        9.99608,
        9.99712,
        9.998,
        9.99872,
        9.99928,
        9.99968,
        9.99992,
        10.0,
        10.0,
        10.0,
        10.0,
        10.0,
        10.0,
        10.0,
        10.0,
        10.0,
        10.0,
        10.0,
        10.0,
        10.0,
        10.0,
        10.0,
        10.0,
        10.0,
        10.0,
        10.0,
        10.0,
        10.0,
        10.0,
        10.0,
        10.0,
        10.0,
        10.0,
        10.0,
        10.0,
        10.0,
        10.0,
        10.0,
        10.0,
        10.0,
        10.0,
        10.0,
        10.0,
        10.0,
        10.0,
        10.0,
        10.0,
        10.0,
        10.0,
        10.0,
        10.0,
        10.0,
        10.0,
        10.0,
        10.0,
        10.0,
        10.0,
        10.0,
        10.0,
        10.0,
        10.0,
        10.0,
        10.0,
        10.0,
        10.0,
        10.0,
        10.0,
        10.0,
        10.0,
        10.0,
        10.0,
        10.0,
        10.0,
        10.0,
        10.0,
        10.0,
        10.0,
        10.0,
        10.0,
        10.0,
        10.0,
        10.0,
        10.0,
        10.0,
        10.0,
        10.0,
        10.0,
        10.0,
        10.0,
        10.0,
        10.0,
        10.0,
        10.0,
        10.0,
        10.0,
        10.0,
        10.0,
        10.0,
        10.0,
        10.0,
        10.0,
        10.0,
        10.0,
        10.0,
        10.0,
        10.0,
        10.0,
        10.0,
        10.0,
        10.0,
        10.0,
        10.0,
        10.0,
        10.0,
        10.0,
        10.0,
        10.0,
        10.0,
        10.0,
        10.0,
        10.0,
        10.0,
        10.0,
        10.0,
        10.0,
        10.0,
        10.0,
        10.0,
        10.0,
        10.0,
        10.0,
        10.0,
        10.0,
        10.0
      ]
    }
  ]
}
