{
  "TRANSFORM.Blocks.Examples.EasingRamp_Test": {
    "filename": "Blocks_EasingRamp_Test.json",
    "last_updated": "2026-04-07T13:55:46.058836+00:00",
    "n_vars": 2
  },
  "TRANSFORM.Blocks.Examples.Easing_Test": {
    "filename": "Blocks_Easing_Test.json",
    "last_updated": "2026-04-07T13:55:46.056279+00:00",
    "n_vars": 2
  },
  "TRANSFORM.Blocks.Examples.ExponentialDecay_Test": {
    "filename": "Blocks_ExponentialDecay_Test.json",
    "last_updated": "2026-04-07T13:55:46.060814+00:00",
    "n_vars": 1
  },
  "TRANSFORM.Blocks.Examples.IntegratorWithReset": {
    "filename": "Blocks_IntegratorWithReset.json",
    "last_updated": "2026-04-07T13:55:46.063053+00:00",
    "n_vars": 4
  },
  "TRANSFORM.Blocks.Examples.LatchHold_Test": {
    "filename": "Blocks_LatchHold_Test.json",
    "last_updated": "2026-04-07T13:55:46.071535+00:00",
    "n_vars": 1
  },
  "TRANSFORM.Blocks.Examples.Latch_Test": {
    "filename": "Blocks_Latch_Test.json",
    "last_updated": "2026-04-07T13:55:46.065330+00:00",
    "n_vars": 1
  },
  "TRANSFORM.Blocks.Examples.MFBS_Test": {
    "filename": "Blocks_MFBS_Test.json",
    "last_updated": "2026-04-07T13:55:46.073366+00:00",
    "n_vars": 1
  },
  "TRANSFORM.Blocks.Examples.OffTimer": {
    "filename": "Blocks_OffTimer.json",
    "last_updated": "2026-04-07T13:55:46.075298+00:00",
    "n_vars": 2
  },
  "TRANSFORM.Blocks.Examples.PRBS_Test": {
    "filename": "Blocks_PRBS_Test.json",
    "last_updated": "2026-04-07T13:55:46.077365+00:00",
    "n_vars": 1
  },
  "TRANSFORM.Blocks.Examples.PRTS_Test": {
    "filename": "Blocks_PRTS_Test.json",
    "last_updated": "2026-04-07T13:55:46.079318+00:00",
    "n_vars": 1
  },
  "TRANSFORM.Blocks.Examples.SwitchHold_Test": {
    "filename": "Blocks_SwitchHold_Test.json",
    "last_updated": "2026-04-07T13:55:46.081302+00:00",
    "n_vars": 1
  },
  "TRANSFORM.Controls.Examples.FeedForward.getOpening_ValveIncompressible_Test": {
    "filename": "Controls_FeedForward_getOpening_ValveIncompressible_Test.json",
    "last_updated": "2026-04-07T13:55:46.083310+00:00",
    "n_vars": 2
  },
  "TRANSFORM.Controls.Examples.FeedForward.getRPM_centrifugalPump_Test": {
    "filename": "Controls_FeedForward_getRPM_centrifugalPump_Test.json",
    "last_updated": "2026-04-07T13:55:46.085397+00:00",
    "n_vars": 2
  },
  "TRANSFORM.Controls.Examples.LimPID_HysteresisTimer_Test": {
    "filename": "Controls_LimPID_HysteresisTimer_Test.json",
    "last_updated": "2026-04-07T13:55:46.089940+00:00",
    "n_vars": 2
  },
  "TRANSFORM.Controls.Examples.LimPID_Hysteresis_Test": {
    "filename": "Controls_LimPID_Hysteresis_Test.json",
    "last_updated": "2026-04-07T13:55:46.087755+00:00",
    "n_vars": 2
  },
  "TRANSFORM.Controls.Examples.LimPID_Test": {
    "filename": "Controls_LimPID_Test.json",
    "last_updated": "2026-04-07T13:55:46.092132+00:00",
    "n_vars": 3
  },
  "TRANSFORM.Controls.Examples.LimPID_withReset_Test": {
    "filename": "Controls_LimPID_withReset_Test.json",
    "last_updated": "2026-04-07T13:55:46.094633+00:00",
    "n_vars": 4
  },
  "TRANSFORM.Electrical.Examples.SimpleBattery_Test": {
    "filename": "Electrical_SimpleBattery_Test.json",
    "last_updated": "2026-04-07T13:55:46.097050+00:00",
    "n_vars": 1
  },
  "TRANSFORM.Examples.CIET_Facility.Examples.CIET_nureth": {
    "filename": "CIET_Facility_CIET_nureth.json",
    "last_updated": "2026-04-07T13:55:46.099066+00:00",
    "n_vars": 1
  },
  "TRANSFORM.Examples.Demonstrations.Examples.BatemanEquations_Test": {
    "filename": "Demonstrations_BatemanEquations_Test.json",
    "last_updated": "2026-04-07T13:55:46.101327+00:00",
    "n_vars": 4
  },
  "TRANSFORM.Examples.Demonstrations.Examples.LorenzSystem_LinA_Test": {
    "filename": "Demonstrations_LorenzSystem_LinA_Test.json",
    "last_updated": "2026-04-07T13:55:46.103916+00:00",
    "n_vars": 3
  },
  "TRANSFORM.Examples.Demonstrations.Examples.LorenzSystem_Test": {
    "filename": "Demonstrations_LorenzSystem_Test.json",
    "last_updated": "2026-04-07T13:55:46.106459+00:00",
    "n_vars": 3
  },
  "TRANSFORM.Examples.LightWaterReactor_PWR_Westinghouse.Examples.NSSS_Test": {
    "filename": "LightWaterReactor_PWR_Westinghouse_NSSS_Test.json",
    "last_updated": "2026-04-07T13:55:46.108744+00:00",
    "n_vars": 2
  },
  "TRANSFORM.Examples.LightWaterSmallModularReactor.Examples.IRIS_Default_Teststandalone": {
    "filename": "LightWaterSmallModularReactor_IRIS_Default_Teststandalone.json",
    "last_updated": "2026-04-07T13:55:46.110896+00:00",
    "n_vars": 2
  },
  "TRANSFORM.Examples.SystemOfSubSystems.PHS.Examples.IRIS_Default_Test": {
    "filename": "SystemOfSubSystems_PHS_IRIS_Default_Test.json",
    "last_updated": "2026-04-07T13:55:46.113025+00:00",
    "n_vars": 2
  },
  "TRANSFORM.Fluid.ClosureRelations.HeatTransfer.Models.Examples.DistributedPipe_1D_MultiTransferSurface.check_Alphas_F1D": {
    "filename": "Fluid_CR_HT_DistributedPipe_1D_MultiTransferSurface_check_Alphas_F1D.json",
    "last_updated": "2026-04-07T13:55:46.115298+00:00",
    "n_vars": 4
  },
  "TRANSFORM.Fluid.ClosureRelations.HeatTransfer.Models.Examples.DistributedPipe_1D_MultiTransferSurface.check_Alphas_TwoPhase_3Region_CHFtransition_F1D": {
    "filename": "Fluid_CR_HT_DistributedPipe_1D_MultiTransferSurface_check_Alphas_TwoPhase_3Region_CHFtransition_F1D.json",
    "last_updated": "2026-04-07T13:55:46.117941+00:00",
    "n_vars": 4
  },
  "TRANSFORM.Fluid.ClosureRelations.HeatTransfer.Models.Examples.DistributedPipe_1D_MultiTransferSurface.check_Alphas_TwoPhase_3Region_F1D": {
    "filename": "Fluid_CR_HT_DistributedPipe_1D_MultiTransferSurface_check_Alphas_TwoPhase_3Region_F1D.json",
    "last_updated": "2026-04-07T13:55:46.120722+00:00",
    "n_vars": 4
  },
  "TRANSFORM.Fluid.ClosureRelations.HeatTransfer.Models.Examples.DistributedPipe_1D_MultiTransferSurface.check_Alphas_TwoPhase_4Region_F1D": {
    "filename": "Fluid_CR_HT_DistributedPipe_1D_MultiTransferSurface_check_Alphas_TwoPhase_4Region_F1D.json",
    "last_updated": "2026-04-07T13:55:46.123368+00:00",
    "n_vars": 4
  },
  "TRANSFORM.Fluid.ClosureRelations.HeatTransfer.Models.Examples.DistributedPipe_1D_MultiTransferSurface.check_Alphas_TwoPhase_5Region_F1D": {
    "filename": "Fluid_CR_HT_DistributedPipe_1D_MultiTransferSurface_check_Alphas_TwoPhase_5Region_F1D.json",
    "last_updated": "2026-04-07T13:55:46.125918+00:00",
    "n_vars": 4
  },
  "TRANSFORM.Fluid.ClosureRelations.HeatTransfer.Models.Examples.DistributedPipe_1D_MultiTransferSurface.check_Ideal_F1D": {
    "filename": "Fluid_CR_HT_DistributedPipe_1D_MultiTransferSurface_check_Ideal_F1D.json",
    "last_updated": "2026-04-07T13:55:46.128167+00:00",
    "n_vars": 4
  },
  "TRANSFORM.Fluid.ClosureRelations.HeatTransfer.Models.Examples.DistributedPipe_1D_MultiTransferSurface.check_Nus_DittusBoelter_Simple_F1D": {
    "filename": "Fluid_CR_HT_DistributedPipe_1D_MultiTransferSurface_check_Nus_DittusBoelter_Simple_F1D.json",
    "last_updated": "2026-04-07T13:55:46.130228+00:00",
    "n_vars": 4
  },
  "TRANSFORM.Fluid.ClosureRelations.HeatTransfer.Models.Examples.DistributedPipe_1D_MultiTransferSurface.check_Nus_F1D": {
    "filename": "Fluid_CR_HT_DistributedPipe_1D_MultiTransferSurface_check_Nus_F1D.json",
    "last_updated": "2026-04-07T13:55:46.132836+00:00",
    "n_vars": 4
  },
  "TRANSFORM.Fluid.ClosureRelations.HeatTransfer.Models.Examples.DistributedPipe_1D_MultiTransferSurface.check_Nus_SinglePhase_2Region_F1D": {
    "filename": "Fluid_CR_HT_DistributedPipe_1D_MultiTransferSurface_check_Nus_SinglePhase_2Region_F1D.json",
    "last_updated": "2026-04-07T13:55:46.135351+00:00",
    "n_vars": 4
  },
  "TRANSFORM.Fluid.ClosureRelations.HeatTransfer.Models.Examples.DistributedPipe_1D_MultiTransferSurface.check_Nus_SinglePhase_2Region_F1D_modelBased": {
    "filename": "Fluid_CR_HT_DistributedPipe_1D_MultiTransferSurface_check_Nus_SinglePhase_2Region_F1D_modelBased.json",
    "last_updated": "2026-04-07T13:55:46.137997+00:00",
    "n_vars": 4
  },
  "TRANSFORM.Fluid.ClosureRelations.HeatTransfer.Models.Examples.Lumped.check_Alphas_FL": {
    "filename": "Fluid_CR_HT_Lumped_check_Alphas_FL.json",
    "last_updated": "2026-04-07T13:55:46.140752+00:00",
    "n_vars": 4
  },
  "TRANSFORM.Fluid.ClosureRelations.HeatTransfer.Models.Examples.Lumped.check_Ideal_FL": {
    "filename": "Fluid_CR_HT_Lumped_check_Ideal_FL.json",
    "last_updated": "2026-04-07T13:55:46.142903+00:00",
    "n_vars": 4
  },
  "TRANSFORM.Fluid.ClosureRelations.HeatTransfer.Models.Examples.Lumped.check_Nus_FL": {
    "filename": "Fluid_CR_HT_Lumped_check_Nus_FL.json",
    "last_updated": "2026-04-07T13:55:46.144991+00:00",
    "n_vars": 4
  },
  "TRANSFORM.Fluid.ClosureRelations.HeatTransfer.Models.Examples.Lumped.check_Nus_SinglePhase_2Region_FL": {
    "filename": "Fluid_CR_HT_Lumped_check_Nus_SinglePhase_2Region_FL.json",
    "last_updated": "2026-04-07T13:55:46.147540+00:00",
    "n_vars": 4
  },
  "TRANSFORM.Fluid.ClosureRelations.PressureLoss.Functions.Examples.Utilities.TwoPhaseFrictionMultiplier": {
    "filename": "Fluid_CR_PL_Fn_Utilities_TwoPhaseFrictionMultiplier.json",
    "last_updated": "2026-04-07T13:55:46.150123+00:00",
    "n_vars": 2
  },
  "TRANSFORM.Fluid.Examples.MSLFluid.BranchingDynamicPipes": {
    "filename": "Fluid_MSLFluid_BranchingDynamicPipes.json",
    "last_updated": "2026-04-07T13:55:46.152521+00:00",
    "n_vars": 10
  },
  "TRANSFORM.Fluid.Examples.MSLFluid.BranchingDynamicPipes_MultiSurface": {
    "filename": "Fluid_MSLFluid_BranchingDynamicPipes_MultiSurface.json",
    "last_updated": "2026-04-07T13:55:46.156453+00:00",
    "n_vars": 10
  },
  "TRANSFORM.Fluid.Examples.MSLFluid.HeatingSystem": {
    "filename": "Fluid_MSLFluid_HeatingSystem.json",
    "last_updated": "2026-04-07T13:55:46.159829+00:00",
    "n_vars": 3
  },
  "TRANSFORM.Fluid.Examples.MSLFluid.IncompressibleFluidNetwork": {
    "filename": "Fluid_MSLFluid_IncompressibleFluidNetwork.json",
    "last_updated": "2026-04-07T13:55:46.162123+00:00",
    "n_vars": 2
  },
  "TRANSFORM.Fluid.Examples.MSLFluid.InverseParameterization": {
    "filename": "Fluid_MSLFluid_InverseParameterization.json",
    "last_updated": "2026-04-07T13:55:46.164522+00:00",
    "n_vars": 1
  },
  "TRANSFORM.Fluid.Examples.MSLFluid.PumpingSystem": {
    "filename": "Fluid_MSLFluid_PumpingSystem.json",
    "last_updated": "2026-04-07T13:55:46.166578+00:00",
    "n_vars": 1
  },
  "TRANSFORM.Fluid.Examples.MSLFluid.RoomCO2WithControls": {
    "filename": "Fluid_MSLFluid_RoomCO2WithControls.json",
    "last_updated": "2026-04-07T13:55:46.168550+00:00",
    "n_vars": 1
  },
  "TRANSFORM.Fluid.Examples.NaturalCirculation": {
    "filename": "Fluid_NaturalCirculation.json",
    "last_updated": "2026-04-07T13:55:46.170725+00:00",
    "n_vars": 3
  },
  "TRANSFORM.Fluid.Examples.NaturalCirculation2": {
    "filename": "Fluid_NaturalCirculation2.json",
    "last_updated": "2026-04-07T13:55:46.173063+00:00",
    "n_vars": 3
  },
  "TRANSFORM.Fluid.Examples.RankineCycle": {
    "filename": "Fluid_RankineCycle.json",
    "last_updated": "2026-04-07T13:55:46.175398+00:00",
    "n_vars": 1
  },
  "TRANSFORM.Fluid.Examples.TritiumExamples.HumTest": {
    "filename": "Fluid_TritiumHumTest.json",
    "last_updated": "2026-04-07T13:55:46.177451+00:00",
    "n_vars": 1
  },
  "TRANSFORM.Fluid.Examples.TritiumExamples.PbLiTest2": {
    "filename": "Fluid_TritiumPbLiTest2.json",
    "last_updated": "2026-04-07T13:55:46.179455+00:00",
    "n_vars": 1
  },
  "TRANSFORM.Fluid.Machines.Examples.PumpTests.Pump_Controlled_Test": {
    "filename": "Fluid_Machines_PumpTests_Pump_Controlled_Test.json",
    "last_updated": "2026-04-07T13:55:46.181816+00:00",
    "n_vars": 1
  },
  "TRANSFORM.Fluid.Machines.Examples.PumpTests.Pump_Mechanical_Test": {
    "filename": "Fluid_Machines_PumpTests_Pump_Mechanical_Test.json",
    "last_updated": "2026-04-07T13:55:46.184040+00:00",
    "n_vars": 1
  },
  "TRANSFORM.Fluid.Machines.Examples.SteamTurbineStodolaTests.RankineCycle_Example8_1": {
    "filename": "Fluid_Machines_SteamTurbineStodolaTests_RankineCycle_Example8_1.json",
    "last_updated": "2026-04-07T13:55:46.186094+00:00",
    "n_vars": 1
  },
  "TRANSFORM.Fluid.Machines.Examples.SteamTurbineStodolaTests.RankineCycle_Example8_12": {
    "filename": "Fluid_Machines_SteamTurbineStodolaTests_RankineCycle_Example8_12.json",
    "last_updated": "2026-04-07T13:55:46.188148+00:00",
    "n_vars": 1
  },
  "TRANSFORM.Fluid.Machines.Examples.SteamTurbineStodolaTests.SteamTurbineStodola_Test": {
    "filename": "Fluid_Machines_SteamTurbineStodolaTests_SteamTurbineStodola_Test.json",
    "last_updated": "2026-04-07T13:55:46.192213+00:00",
    "n_vars": 1
  },
  "TRANSFORM.Fluid.Machines.Examples.SteamTurbineStodolaTests.SteamTurbine_Example7_6": {
    "filename": "Fluid_Machines_SteamTurbineStodolaTests_SteamTurbine_Example7_6.json",
    "last_updated": "2026-04-07T13:55:46.190217+00:00",
    "n_vars": 1
  },
  "TRANSFORM.Fluid.Pipes.Examples.GenericPipe_MultiTransferSurface.nParallel_FlowBoundary_MultiTransferSurface": {
    "filename": "Fluid_Pipes_GenericPipe_MultiTransferSurface_nParallel_FlowBoundary_MultiTransferSurface.json",
    "last_updated": "2026-04-07T13:55:46.194446+00:00",
    "n_vars": 4
  },
  "TRANSFORM.Fluid.Pipes.Examples.GenericPipe_Tests.nParallel_FlowBoundary": {
    "filename": "Fluid_Pipes_GenericPipe_Tests_nParallel_FlowBoundary.json",
    "last_updated": "2026-04-07T13:55:46.196954+00:00",
    "n_vars": 4
  },
  "TRANSFORM.Fluid.Pipes.Examples.GenericPipe_Tests.nParallel_StateBoundary": {
    "filename": "Fluid_Pipes_GenericPipe_Tests_nParallel_StateBoundary.json",
    "last_updated": "2026-04-07T13:55:46.199264+00:00",
    "n_vars": 4
  },
  "TRANSFORM.Fluid.Pipes.Examples.GenericPipe_Tests.nParallel_withWall_FlowBoundary": {
    "filename": "Fluid_Pipes_GenericPipe_Tests_nParallel_withWall_FlowBoundary.json",
    "last_updated": "2026-04-07T13:55:46.201397+00:00",
    "n_vars": 4
  },
  "TRANSFORM.Fluid.Pipes.Examples.GenericPipe_Tests.nParallel_withWall_StateBoundary": {
    "filename": "Fluid_Pipes_GenericPipe_Tests_nParallel_withWall_StateBoundary.json",
    "last_updated": "2026-04-07T13:55:46.203661+00:00",
    "n_vars": 4
  },
  "TRANSFORM.Fluid.Pipes.Examples.GenericPipe_Tests.withWall": {
    "filename": "Fluid_Pipes_GenericPipe_Tests_withWall.json",
    "last_updated": "2026-04-07T13:55:46.205744+00:00",
    "n_vars": 1
  },
  "TRANSFORM.Fluid.Pipes.Examples.GenericPipe_Tests.withWallTrace": {
    "filename": "Fluid_Pipes_GenericPipe_Tests_withWallTrace.json",
    "last_updated": "2026-04-07T13:55:46.207872+00:00",
    "n_vars": 2
  },
  "TRANSFORM.Fluid.Pipes.Examples.GenericPipe_Tests.withWallx2": {
    "filename": "Fluid_Pipes_GenericPipe_Tests_withWallx2.json",
    "last_updated": "2026-04-07T13:55:46.210043+00:00",
    "n_vars": 1
  },
  "TRANSFORM.Fluid.Pipes.Examples.TransportDelayPipeTests.CheckDelayTime": {
    "filename": "Fluid_Pipes_TransportDelayPipeTests_CheckDelayTime.json",
    "last_updated": "2026-04-07T13:55:46.212270+00:00",
    "n_vars": 3
  },
  "TRANSFORM.Fluid.Pipes.Examples.TransportDelayPipeTests.Test1_MultiSpeciesMultiTrace": {
    "filename": "Fluid_Pipes_TransportDelayPipeTests_Test1_MultiSpeciesMultiTrace.json",
    "last_updated": "2026-04-07T13:55:46.214620+00:00",
    "n_vars": 3
  },
  "TRANSFORM.Fluid.Pipes.Examples.TransportDelayPipeTests.Test2_MultiSpeciesMultiTrace": {
    "filename": "Fluid_Pipes_TransportDelayPipeTests_Test2_MultiSpeciesMultiTrace.json",
    "last_updated": "2026-04-07T13:55:46.216851+00:00",
    "n_vars": 3
  },
  "TRANSFORM.Fluid.Pipes.Examples.UseOfGeometryModel": {
    "filename": "Fluid_Pipes_UseOfGeometryModel.json",
    "last_updated": "2026-04-07T13:55:46.219295+00:00",
    "n_vars": 2
  },
  "TRANSFORM.Fluid.TraceComponents.Examples.TraceDecayAdsorberBed_Test": {
    "filename": "Fluid_TraceComponents_TraceDecayAdsorberBed_Test.json",
    "last_updated": "2026-04-07T13:55:46.221466+00:00",
    "n_vars": 2
  },
  "TRANSFORM.Fluid.TraceComponents.Examples.TraceSeparator_Test": {
    "filename": "Fluid_TraceComponents_TraceSeparator_Test.json",
    "last_updated": "2026-04-07T13:55:46.223613+00:00",
    "n_vars": 5
  },
  "TRANSFORM.Fluid.Valves.Examples.CheckValve_Test": {
    "filename": "Fluid_Valves_CheckValve_Test.json",
    "last_updated": "2026-04-07T13:55:46.225537+00:00",
    "n_vars": 2
  },
  "TRANSFORM.Fluid.Volumes.Examples.Condenser_Test": {
    "filename": "Fluid_Volumes_Condenser_Test.json",
    "last_updated": "2026-04-07T13:55:46.227678+00:00",
    "n_vars": 1
  },
  "TRANSFORM.Fluid.Volumes.Examples.DumpTank_Test": {
    "filename": "Fluid_Volumes_DumpTank_Test.json",
    "last_updated": "2026-04-07T13:55:46.229684+00:00",
    "n_vars": 1
  },
  "TRANSFORM.Fluid.Volumes.Examples.ExpansionTank2_Test": {
    "filename": "Fluid_Volumes_ExpansionTank2_Test.json",
    "last_updated": "2026-04-07T13:55:46.231786+00:00",
    "n_vars": 2
  },
  "TRANSFORM.Fluid.Volumes.Examples.ExpansionTank_Test": {
    "filename": "Fluid_Volumes_ExpansionTank_Test.json",
    "last_updated": "2026-04-07T13:55:46.234172+00:00",
    "n_vars": 2
  },
  "TRANSFORM.Fluid.Volumes.Examples.IdealCondenser_Test": {
    "filename": "Fluid_Volumes_IdealCondenser_Test.json",
    "last_updated": "2026-04-07T13:55:46.236307+00:00",
    "n_vars": 1
  },
  "TRANSFORM.Fluid.Volumes.Examples.MixingVolume_Test": {
    "filename": "Fluid_Volumes_MixingVolume_Test.json",
    "last_updated": "2026-04-07T13:55:46.238334+00:00",
    "n_vars": 2
  },
  "TRANSFORM.Fluid.Volumes.Examples.Pressurizer_Simple_Test": {
    "filename": "Fluid_Volumes_Pressurizer_Simple_Test.json",
    "last_updated": "2026-04-07T13:55:46.240549+00:00",
    "n_vars": 1
  },
  "TRANSFORM.Fluid.Volumes.Examples.Pressurizer_Test": {
    "filename": "Fluid_Volumes_Pressurizer_Test.json",
    "last_updated": "2026-04-07T13:55:46.242674+00:00",
    "n_vars": 1
  },
  "TRANSFORM.Fluid.Volumes.Examples.Pressurizer_withWall_Test": {
    "filename": "Fluid_Volumes_Pressurizer_withWall_Test.json",
    "last_updated": "2026-04-07T13:55:46.244696+00:00",
    "n_vars": 1
  },
  "TRANSFORM.Fluid.Volumes.Examples.Seperator_2PhaseOnly_Test": {
    "filename": "Fluid_Volumes_Seperator_2PhaseOnly_Test.json",
    "last_updated": "2026-04-07T13:55:46.246973+00:00",
    "n_vars": 1
  },
  "TRANSFORM.Fluid.Volumes.Examples.Seperator_Test": {
    "filename": "Fluid_Volumes_Seperator_Test.json",
    "last_updated": "2026-04-07T13:55:46.249056+00:00",
    "n_vars": 2
  },
  "TRANSFORM.Fluid.Volumes.Examples.SimpleVolume_Test": {
    "filename": "Fluid_Volumes_SimpleVolume_Test.json",
    "last_updated": "2026-04-07T13:55:46.251383+00:00",
    "n_vars": 2
  },
  "TRANSFORM.HeatAndMassTransfer.ClosureRelations.HeatTransfer.Functions.Examples.SinglePhase.ExternalFlow.LiquidMetal.check_Nu_Borishanskii": {
    "filename": "HAMT_CR_HT_Fn_SinglePhase_ExternalFlow_LiquidMetal_check_Nu_Borishanskii.json",
    "last_updated": "2026-04-07T13:55:46.255918+00:00",
    "n_vars": 1
  },
  "TRANSFORM.HeatAndMassTransfer.ClosureRelations.HeatTransfer.Functions.Examples.SinglePhase.ExternalFlow.LiquidMetal.check_Nu_FFTF": {
    "filename": "HAMT_CR_HT_Fn_SinglePhase_ExternalFlow_LiquidMetal_check_Nu_FFTF.json",
    "last_updated": "2026-04-07T13:55:46.258076+00:00",
    "n_vars": 1
  },
  "TRANSFORM.HeatAndMassTransfer.ClosureRelations.HeatTransfer.Functions.Examples.SinglePhase.ExternalFlow.LiquidMetal.check_Nu_GraberRieger": {
    "filename": "HAMT_CR_HT_Fn_SinglePhase_ExternalFlow_LiquidMetal_check_Nu_GraberRieger.json",
    "last_updated": "2026-04-07T13:55:46.260179+00:00",
    "n_vars": 1
  },
  "TRANSFORM.HeatAndMassTransfer.ClosureRelations.HeatTransfer.Functions.Examples.SinglePhase.ExternalFlow.LiquidMetal.check_Nu_modifiedSchad": {
    "filename": "HAMT_CR_HT_Fn_SinglePhase_ExternalFlow_LiquidMetal_check_Nu_modifiedSchad.json",
    "last_updated": "2026-04-07T13:55:46.262330+00:00",
    "n_vars": 1
  },
  "TRANSFORM.HeatAndMassTransfer.ClosureRelations.HeatTransfer.Functions.Examples.SinglePhase.ExternalFlow.check_Nu_Grimison_FlowAcrossTubeBanks": {
    "filename": "HAMT_CR_HT_Fn_SinglePhase_ExternalFlow_check_Nu_Grimison_FlowAcrossTubeBanks.json",
    "last_updated": "2026-04-07T13:55:46.253667+00:00",
    "n_vars": 2
  },
  "TRANSFORM.HeatAndMassTransfer.ClosureRelations.HeatTransfer.Functions.Examples.SinglePhase.InternalFlow.check_Nu_DittusBoelter": {
    "filename": "HAMT_CR_HT_Fn_SinglePhase_InternalFlow_check_Nu_DittusBoelter.json",
    "last_updated": "2026-04-07T13:55:46.264457+00:00",
    "n_vars": 1
  },
  "TRANSFORM.HeatAndMassTransfer.ClosureRelations.HeatTransfer.Functions.Examples.SinglePhase.InternalFlow.check_Nu_Laminar_Local_Developed_Circular": {
    "filename": "HAMT_CR_HT_Fn_SinglePhase_InternalFlow_check_Nu_Laminar_Local_Developed_Circular.json",
    "last_updated": "2026-04-07T13:55:46.266525+00:00",
    "n_vars": 2
  },
  "TRANSFORM.HeatAndMassTransfer.ClosureRelations.HeatTransfer.Functions.Examples.SinglePhase.InternalFlow.check_Nu_Laminar_Local_Developed_Rectangular": {
    "filename": "HAMT_CR_HT_Fn_SinglePhase_InternalFlow_check_Nu_Laminar_Local_Developed_Rectangular.json",
    "last_updated": "2026-04-07T13:55:46.269022+00:00",
    "n_vars": 2
  },
  "TRANSFORM.HeatAndMassTransfer.ClosureRelations.HeatTransfer.Functions.Examples.SinglePhase.InternalFlow.check_Nu_LiquidMetal_Developed_Circular": {
    "filename": "HAMT_CR_HT_Fn_SinglePhase_InternalFlow_check_Nu_LiquidMetal_Developed_Circular.json",
    "last_updated": "2026-04-07T13:55:46.271417+00:00",
    "n_vars": 2
  },
  "TRANSFORM.HeatAndMassTransfer.ClosureRelations.HeatTransfer.Functions.Examples.SinglePhase.InternalFlow.check_Nu_Overall_Local_Developed_Circular": {
    "filename": "HAMT_CR_HT_Fn_SinglePhase_InternalFlow_check_Nu_Overall_Local_Developed_Circular.json",
    "last_updated": "2026-04-07T13:55:46.273679+00:00",
    "n_vars": 2
  },
  "TRANSFORM.HeatAndMassTransfer.ClosureRelations.HeatTransfer.Functions.Examples.SinglePhase.InternalFlow.check_Nu_SiederTate": {
    "filename": "HAMT_CR_HT_Fn_SinglePhase_InternalFlow_check_Nu_SiederTate.json",
    "last_updated": "2026-04-07T13:55:46.275929+00:00",
    "n_vars": 1
  },
  "TRANSFORM.HeatAndMassTransfer.ClosureRelations.HeatTransfer.Functions.Examples.SinglePhase.InternalFlow.check_Nu_Turbulent_Local_Developed": {
    "filename": "HAMT_CR_HT_Fn_SinglePhase_InternalFlow_check_Nu_Turbulent_Local_Developed.json",
    "last_updated": "2026-04-07T13:55:46.278045+00:00",
    "n_vars": 2
  },
  "TRANSFORM.HeatAndMassTransfer.ClosureRelations.HeatTransfer.Functions.Examples.TwoPhase.NucleateBoiling.alpha_Chen_FvsInvXtt": {
    "filename": "HAMT_CR_HT_Fn_TwoPhase_NucleateBoiling_alpha_Chen_FvsInvXtt.json",
    "last_updated": "2026-04-07T13:55:46.280480+00:00",
    "n_vars": 3
  },
  "TRANSFORM.HeatAndMassTransfer.ClosureRelations.HeatTransfer.Functions.Examples.TwoPhase.NucleateBoiling.alpha_Chen_SvsRe": {
    "filename": "HAMT_CR_HT_Fn_TwoPhase_NucleateBoiling_alpha_Chen_SvsRe.json",
    "last_updated": "2026-04-07T13:55:46.282957+00:00",
    "n_vars": 3
  },
  "TRANSFORM.HeatAndMassTransfer.ClosureRelations.HeatTransfer.Functions.Examples.TwoPhase.PostCHF.alpha_Groeneveld": {
    "filename": "HAMT_CR_HT_Fn_TwoPhase_PostCHF_alpha_Groeneveld.json",
    "last_updated": "2026-04-07T13:55:46.285203+00:00",
    "n_vars": 1
  },
  "TRANSFORM.HeatAndMassTransfer.ClosureRelations.HeatTransfer.Functions.Examples.TwoPhase.PostCHF.alpha_Groeneveld_wMedia": {
    "filename": "HAMT_CR_HT_Fn_TwoPhase_PostCHF_alpha_Groeneveld_wMedia.json",
    "last_updated": "2026-04-07T13:55:46.287101+00:00",
    "n_vars": 1
  },
  "TRANSFORM.HeatAndMassTransfer.ClosureRelations.HeatTransfer.Models.Examples.Utilities.Groeneveld2001LUT_FilmBoilingCoefficient": {
    "filename": "HAMT_CR_HT_Models_Utilities_Groeneveld2001LUT_FilmBoilingCoefficient.json",
    "last_updated": "2026-04-07T13:55:46.300444+00:00",
    "n_vars": 5
  },
  "TRANSFORM.HeatAndMassTransfer.ClosureRelations.HeatTransfer.Models.Examples.Utilities.Groeneveld2006LUT": {
    "filename": "HAMT_CR_HT_Models_Utilities_Groeneveld2006LUT.json",
    "last_updated": "2026-04-07T13:55:46.303213+00:00",
    "n_vars": 4
  },
  "TRANSFORM.HeatAndMassTransfer.ClosureRelations.HeatTransfer.Models.Examples.Utilities.Groeneveld2006LUT_withKs": {
    "filename": "HAMT_CR_HT_Models_Utilities_Groeneveld2006LUT_withKs.json",
    "last_updated": "2026-04-07T13:55:46.305883+00:00",
    "n_vars": 4
  },
  "TRANSFORM.HeatAndMassTransfer.ClosureRelations.HeatTransfer.Models.Examples.check_Alphas": {
    "filename": "HAMT_CR_HT_Models_check_Alphas.json",
    "last_updated": "2026-04-07T13:55:46.288945+00:00",
    "n_vars": 2
  },
  "TRANSFORM.HeatAndMassTransfer.ClosureRelations.HeatTransfer.Models.Examples.check_Alphas_TwoPhase_5Region": {
    "filename": "HAMT_CR_HT_Models_check_Alphas_TwoPhase_5Region.json",
    "last_updated": "2026-04-07T13:55:46.290957+00:00",
    "n_vars": 2
  },
  "TRANSFORM.HeatAndMassTransfer.ClosureRelations.HeatTransfer.Models.Examples.check_Ideal": {
    "filename": "HAMT_CR_HT_Models_check_Ideal.json",
    "last_updated": "2026-04-07T13:55:46.293077+00:00",
    "n_vars": 2
  },
  "TRANSFORM.HeatAndMassTransfer.ClosureRelations.HeatTransfer.Models.Examples.check_Nus": {
    "filename": "HAMT_CR_HT_Models_check_Nus.json",
    "last_updated": "2026-04-07T13:55:46.295111+00:00",
    "n_vars": 2
  },
  "TRANSFORM.HeatAndMassTransfer.ClosureRelations.HeatTransfer.Models.Examples.check_Nus_SinglePhase_2Region": {
    "filename": "HAMT_CR_HT_Models_check_Nus_SinglePhase_2Region.json",
    "last_updated": "2026-04-07T13:55:46.297862+00:00",
    "n_vars": 2
  },
  "TRANSFORM.HeatAndMassTransfer.Examples.ClosedGeometry_Test": {
    "filename": "HAMT_ClosedGeometry_Test.json",
    "last_updated": "2026-04-07T13:55:46.309864+00:00",
    "n_vars": 24
  },
  "TRANSFORM.HeatAndMassTransfer.Examples.ExamplesFrom_IncroperaAndDeWitt.Example_8_6_UninsulatedDuct": {
    "filename": "HAMT_ExamplesFrom_IncroperaAndDeWitt_Example_8_6_UninsulatedDuct.json",
    "last_updated": "2026-04-07T13:55:46.314739+00:00",
    "n_vars": 3
  },
  "TRANSFORM.HeatAndMassTransfer.Examples.ExamplesFrom_IncroperaAndDeWitt.Example_8_6_UninsulatedDuctwithMass": {
    "filename": "HAMT_ExamplesFrom_IncroperaAndDeWitt_Example_8_6_UninsulatedDuctwithMass.json",
    "last_updated": "2026-04-07T13:55:46.317084+00:00",
    "n_vars": 2
  },
  "TRANSFORM.HeatAndMassTransfer.Examples.ExamplesFrom_NellisAndKlein.ConveyorBeltDesign": {
    "filename": "HAMT_ExamplesFrom_NellisAndKlein_ConveyorBeltDesign.json",
    "last_updated": "2026-04-07T13:55:46.319252+00:00",
    "n_vars": 1
  },
  "TRANSFORM.HeatAndMassTransfer.Examples.ExamplesFrom_NellisAndKlein.Example_1_2_1_LiquidOxygenDewar.part_ab_ThermalResistances": {
    "filename": "HAMT_ExamplesFrom_NellisAndKlein_Example_1_2_1_LiquidOxygenDewar_part_ab_ThermalResistances.json",
    "last_updated": "2026-04-07T13:55:46.321441+00:00",
    "n_vars": 1
  },
  "TRANSFORM.HeatAndMassTransfer.Examples.ExamplesFrom_NellisAndKlein.Example_1_2_1_LiquidOxygenDewar.part_c_InsulationThickness": {
    "filename": "HAMT_ExamplesFrom_NellisAndKlein_Example_1_2_1_LiquidOxygenDewar_part_c_InsulationThickness.json",
    "last_updated": "2026-04-07T13:55:46.323340+00:00",
    "n_vars": 1
  },
  "TRANSFORM.HeatAndMassTransfer.Examples.ExamplesFrom_NellisAndKlein.Example_1_3_1_MagneticAblation.part_a_TemperatureThermoseedTissue": {
    "filename": "HAMT_ExamplesFrom_NellisAndKlein_Example_1_3_1_MagneticAblation_part_a_TemperatureThermoseedTissue.json",
    "last_updated": "2026-04-07T13:55:46.325695+00:00",
    "n_vars": 3
  },
  "TRANSFORM.HeatAndMassTransfer.Examples.ExamplesFrom_NellisAndKlein.Example_1_3_1_MagneticAblation.part_b1_LesionExtent": {
    "filename": "HAMT_ExamplesFrom_NellisAndKlein_Example_1_3_1_MagneticAblation_part_b1_LesionExtent.json",
    "last_updated": "2026-04-07T13:55:46.328397+00:00",
    "n_vars": 3
  },
  "TRANSFORM.HeatAndMassTransfer.Examples.ExamplesFrom_NellisAndKlein.Example_1_3_1_MagneticAblation.part_b2_LesionExtentwithBloodPerfusion": {
    "filename": "HAMT_ExamplesFrom_NellisAndKlein_Example_1_3_1_MagneticAblation_part_b2_LesionExtentwithBloodPerfusion.json",
    "last_updated": "2026-04-07T13:55:46.330821+00:00",
    "n_vars": 3
  },
  "TRANSFORM.HeatAndMassTransfer.Examples.ExamplesFrom_NellisAndKlein.Example_1_3_2_AbsorptionInALens": {
    "filename": "HAMT_ExamplesFrom_NellisAndKlein_Example_1_3_2_AbsorptionInALens.json",
    "last_updated": "2026-04-07T13:55:46.333254+00:00",
    "n_vars": 1
  },
  "TRANSFORM.HeatAndMassTransfer.Examples.ExamplesFrom_NellisAndKlein.Example_1_4_1_FuelElement": {
    "filename": "HAMT_ExamplesFrom_NellisAndKlein_Example_1_4_1_FuelElement.json",
    "last_updated": "2026-04-07T13:55:46.335582+00:00",
    "n_vars": 3
  },
  "TRANSFORM.HeatAndMassTransfer.Examples.ExamplesFrom_NellisAndKlein.Example_1_5_1_ThermalProtectionSystem": {
    "filename": "HAMT_ExamplesFrom_NellisAndKlein_Example_1_5_1_ThermalProtectionSystem.json",
    "last_updated": "2026-04-07T13:55:46.337911+00:00",
    "n_vars": 1
  },
  "TRANSFORM.HeatAndMassTransfer.Examples.ExamplesFrom_NellisAndKlein.Example_1_6_1_SolderingTubes.part_a_EstimateHeatTransfer": {
    "filename": "HAMT_ExamplesFrom_NellisAndKlein_Example_1_6_1_SolderingTubes_part_a_EstimateHeatTransfer.json",
    "last_updated": "2026-04-07T13:55:46.340013+00:00",
    "n_vars": 1
  },
  "TRANSFORM.HeatAndMassTransfer.Examples.ExamplesFrom_NellisAndKlein.Example_1_6_1_SolderingTubes.part_b_withInsulatingSleeves": {
    "filename": "HAMT_ExamplesFrom_NellisAndKlein_Example_1_6_1_SolderingTubes_part_b_withInsulatingSleeves.json",
    "last_updated": "2026-04-07T13:55:46.342098+00:00",
    "n_vars": 1
  },
  "TRANSFORM.HeatAndMassTransfer.Examples.ExamplesFrom_NellisAndKlein.Example_1_6_2_ThermoelectricHeatSink": {
    "filename": "HAMT_ExamplesFrom_NellisAndKlein_Example_1_6_2_ThermoelectricHeatSink.json",
    "last_updated": "2026-04-07T13:55:46.344001+00:00",
    "n_vars": 1
  },
  "TRANSFORM.HeatAndMassTransfer.Examples.ExamplesFrom_NellisAndKlein.Example_1_7_1_BentBeamActuator.part_a_AppropriateToUseExtendedSurface": {
    "filename": "HAMT_ExamplesFrom_NellisAndKlein_Example_1_7_1_BentBeamActuator_part_a_AppropriateToUseExtendedSurface.json",
    "last_updated": "2026-04-07T13:55:46.345958+00:00",
    "n_vars": 1
  },
  "TRANSFORM.HeatAndMassTransfer.Examples.ExamplesFrom_NellisAndKlein.Example_1_7_1_BentBeamActuator.part_b_TemperatureAndPosition": {
    "filename": "HAMT_ExamplesFrom_NellisAndKlein_Example_1_7_1_BentBeamActuator_part_b_TemperatureAndPosition.json",
    "last_updated": "2026-04-07T13:55:46.347959+00:00",
    "n_vars": 1
  },
  "TRANSFORM.HeatAndMassTransfer.Examples.ExamplesFrom_NellisAndKlein.Example_1_7_1_BentBeamActuator.part_c_ThermalElongation": {
    "filename": "HAMT_ExamplesFrom_NellisAndKlein_Example_1_7_1_BentBeamActuator_part_c_ThermalElongation.json",
    "last_updated": "2026-04-07T13:55:46.350225+00:00",
    "n_vars": 1
  },
  "TRANSFORM.HeatAndMassTransfer.Examples.ExamplesFrom_NellisAndKlein.Example_1_7_2_DrawingAWire": {
    "filename": "HAMT_ExamplesFrom_NellisAndKlein_Example_1_7_2_DrawingAWire.json",
    "last_updated": "2026-04-07T13:55:46.352446+00:00",
    "n_vars": 1
  },
  "TRANSFORM.HeatAndMassTransfer.Examples.ExamplesFrom_NellisAndKlein.Example_1_8_1_PipeInARoof.part_a_UseExtendedSurface": {
    "filename": "HAMT_ExamplesFrom_NellisAndKlein_Example_1_8_1_PipeInARoof_part_a_UseExtendedSurface.json",
    "last_updated": "2026-04-07T13:55:46.354498+00:00",
    "n_vars": 1
  },
  "TRANSFORM.HeatAndMassTransfer.Examples.ExamplesFrom_NellisAndKlein.Example_1_8_1_PipeInARoof.part_b_CalculateHeatLoss": {
    "filename": "HAMT_ExamplesFrom_NellisAndKlein_Example_1_8_1_PipeInARoof_part_b_CalculateHeatLoss.json",
    "last_updated": "2026-04-07T13:55:46.356576+00:00",
    "n_vars": 1
  },
  "TRANSFORM.HeatAndMassTransfer.Examples.ExamplesFrom_NellisAndKlein.Example_1_9_1_TemperatureSensorMounting": {
    "filename": "HAMT_ExamplesFrom_NellisAndKlein_Example_1_9_1_TemperatureSensorMounting.json",
    "last_updated": "2026-04-07T13:55:46.359157+00:00",
    "n_vars": 3
  },
  "TRANSFORM.HeatAndMassTransfer.Examples.ExamplesFrom_NellisAndKlein.Example_1_9_2_CryogenicCurrentLeads": {
    "filename": "HAMT_ExamplesFrom_NellisAndKlein_Example_1_9_2_CryogenicCurrentLeads.json",
    "last_updated": "2026-04-07T13:55:46.361597+00:00",
    "n_vars": 1
  },
  "TRANSFORM.HeatAndMassTransfer.Examples.ExamplesFrom_NellisAndKlein.Example_2_2_1_2DFin": {
    "filename": "HAMT_ExamplesFrom_NellisAndKlein_Example_2_2_1_2DFin.json",
    "last_updated": "2026-04-07T13:55:46.363750+00:00",
    "n_vars": 2
  },
  "TRANSFORM.HeatAndMassTransfer.Examples.ExamplesFrom_NellisAndKlein.Figure_1_14_NumericalSolutions": {
    "filename": "HAMT_ExamplesFrom_NellisAndKlein_Figure_1_14_NumericalSolutions.json",
    "last_updated": "2026-04-07T13:55:46.366311+00:00",
    "n_vars": 3
  },
  "TRANSFORM.HeatAndMassTransfer.Examples.ExamplesFrom_NellisAndKlein.Figure_1_14_NumericalSolutionsMT": {
    "filename": "HAMT_ExamplesFrom_NellisAndKlein_Figure_1_14_NumericalSolutionsMT.json",
    "last_updated": "2026-04-07T13:55:46.368757+00:00",
    "n_vars": 3
  },
  "TRANSFORM.HeatAndMassTransfer.Examples.ExamplesFrom_NellisAndKlein.Figure_1_8_UniformThermalEnergyGeneration_Plane": {
    "filename": "HAMT_ExamplesFrom_NellisAndKlein_Figure_1_8_UniformThermalEnergyGeneration_Plane.json",
    "last_updated": "2026-04-07T13:55:46.371789+00:00",
    "n_vars": 12
  },
  "TRANSFORM.HeatAndMassTransfer.Examples.ExamplesFrom_NellisAndKlein.OvenBrazing": {
    "filename": "HAMT_ExamplesFrom_NellisAndKlein_OvenBrazing.json",
    "last_updated": "2026-04-07T13:55:46.375268+00:00",
    "n_vars": 1
  },
  "TRANSFORM.HeatAndMassTransfer.Examples.ExamplesFrom_NellisAndKlein.QuenchingACompositeStructure": {
    "filename": "HAMT_ExamplesFrom_NellisAndKlein_QuenchingACompositeStructure.json",
    "last_updated": "2026-04-07T13:55:46.377410+00:00",
    "n_vars": 1
  },
  "TRANSFORM.HeatAndMassTransfer.Examples.ExamplesFrom_NellisAndKlein.SensorInOscillatingTemperatureEnvironment": {
    "filename": "HAMT_ExamplesFrom_NellisAndKlein_SensorInOscillatingTemperatureEnvironment.json",
    "last_updated": "2026-04-07T13:55:46.379677+00:00",
    "n_vars": 1
  },
  "TRANSFORM.HeatAndMassTransfer.Examples.ExamplesFrom_NellisAndKlein.TransientResponseOfATankWall": {
    "filename": "HAMT_ExamplesFrom_NellisAndKlein_TransientResponseOfATankWall.json",
    "last_updated": "2026-04-07T13:55:46.381975+00:00",
    "n_vars": 1
  },
  "TRANSFORM.HeatAndMassTransfer.Examples.ResistanceCheck": {
    "filename": "HAMT_ResistanceCheck.json",
    "last_updated": "2026-04-07T13:55:46.386822+00:00",
    "n_vars": 8
  },
  "TRANSFORM.HeatAndMassTransfer.Examples.WindingDiscretizedModels.Winding_123D": {
    "filename": "HAMT_WindingDiscretizedModels_Winding_123D.json",
    "last_updated": "2026-04-07T13:55:46.388794+00:00",
    "n_vars": 1
  },
  "TRANSFORM.HeatAndMassTransfer.Examples.WindingDiscretizedModels.Winding_123D_variableArea": {
    "filename": "HAMT_WindingDiscretizedModels_Winding_123D_variableArea.json",
    "last_updated": "2026-04-07T13:55:46.390949+00:00",
    "n_vars": 1
  },
  "TRANSFORM.HeatAndMassTransfer.Examples.WindingDiscretizedModels.Winding_123D_withMass": {
    "filename": "HAMT_WindingDiscretizedModels_Winding_123D_withMass.json",
    "last_updated": "2026-04-07T13:55:46.393127+00:00",
    "n_vars": 1
  },
  "TRANSFORM.HeatAndMassTransfer.Examples.WindingDiscretizedModels.Winding_12D": {
    "filename": "HAMT_WindingDiscretizedModels_Winding_12D.json",
    "last_updated": "2026-04-07T13:55:46.395279+00:00",
    "n_vars": 1
  },
  "TRANSFORM.HeatAndMassTransfer.Examples.WindingDiscretizedModels.Winding_12D_variableArea": {
    "filename": "HAMT_WindingDiscretizedModels_Winding_12D_variableArea.json",
    "last_updated": "2026-04-07T13:55:46.397474+00:00",
    "n_vars": 1
  },
  "TRANSFORM.HeatAndMassTransfer.Examples.WindingDiscretizedModels.Winding_12D_withMass": {
    "filename": "HAMT_WindingDiscretizedModels_Winding_12D_withMass.json",
    "last_updated": "2026-04-07T13:55:46.399764+00:00",
    "n_vars": 1
  },
  "TRANSFORM.HeatAndMassTransfer.Examples.nParallel_Test": {
    "filename": "HAMT_nParallel_Test.json",
    "last_updated": "2026-04-07T13:55:46.384317+00:00",
    "n_vars": 8
  },
  "TRANSFORM.HeatExchangers.ClosureRelations.Models.Examples.check_CrossFlow": {
    "filename": "HeatExchangers_ClosureRelations_Models_check_CrossFlow.json",
    "last_updated": "2026-04-07T13:55:46.401828+00:00",
    "n_vars": 2
  },
  "TRANSFORM.HeatExchangers.Examples.OilWater_CTHX": {
    "filename": "HeatExchangers_OilWater_CTHX.json",
    "last_updated": "2026-04-07T13:55:46.404065+00:00",
    "n_vars": 4
  },
  "TRANSFORM.HeatExchangers.Examples.OilWater_PCHX": {
    "filename": "HeatExchangers_OilWater_PCHX.json",
    "last_updated": "2026-04-07T13:55:46.406618+00:00",
    "n_vars": 4
  },
  "TRANSFORM.HeatExchangers.Examples.OilWater_PTHX": {
    "filename": "HeatExchangers_OilWater_PTHX.json",
    "last_updated": "2026-04-07T13:55:46.409137+00:00",
    "n_vars": 4
  },
  "TRANSFORM.HeatExchangers.Examples.SteamWater_HCSG": {
    "filename": "HeatExchangers_SteamWater_HCSG.json",
    "last_updated": "2026-04-07T13:55:46.411595+00:00",
    "n_vars": 4
  },
  "TRANSFORM.HeatExchangers.Examples.UAdT_lm_Example_11_1": {
    "filename": "HeatExchangers_UAdT_lm_Example_11_1.json",
    "last_updated": "2026-04-07T13:55:46.413962+00:00",
    "n_vars": 2
  },
  "TRANSFORM.HeatExchangers.Examples.WaterWater_STHX": {
    "filename": "HeatExchangers_WaterWater_STHX.json",
    "last_updated": "2026-04-07T13:55:46.416317+00:00",
    "n_vars": 4
  },
  "TRANSFORM.HeatExchangers.Examples.WaterWater_STHX_wallR": {
    "filename": "HeatExchangers_WaterWater_STHX_wallR.json",
    "last_updated": "2026-04-07T13:55:46.419155+00:00",
    "n_vars": 4
  },
  "TRANSFORM.HeatExchangers.Examples.WaterWater_STHX_withMass": {
    "filename": "HeatExchangers_WaterWater_STHX_withMass.json",
    "last_updated": "2026-04-07T13:55:46.422200+00:00",
    "n_vars": 3
  },
  "TRANSFORM.HeatExchangers.Sizing.Examples.Sizing_CrossflowHX": {
    "filename": "HeatExchangers_Sizing_Sizing_CrossflowHX.json",
    "last_updated": "2026-04-07T13:55:46.424647+00:00",
    "n_vars": 2
  },
  "TRANSFORM.Math.Examples.ComplexMath.check_ccubicRoots": {
    "filename": "Math_ComplexMath_check_ccubicRoots.json",
    "last_updated": "2026-04-07T13:55:46.513765+00:00",
    "n_vars": 2
  },
  "TRANSFORM.Math.Examples.ComplexMath.check_csqrt": {
    "filename": "Math_ComplexMath_check_csqrt.json",
    "last_updated": "2026-04-07T13:55:46.515753+00:00",
    "n_vars": 2
  },
  "TRANSFORM.Math.Examples.check_BesselJ": {
    "filename": "Math_check_BesselJ.json",
    "last_updated": "2026-04-07T13:55:46.428843+00:00",
    "n_vars": 2
  },
  "TRANSFORM.Math.Examples.check_arrheniusEquation": {
    "filename": "Math_check_arrheniusEquation.json",
    "last_updated": "2026-04-07T13:55:46.426646+00:00",
    "n_vars": 1
  },
  "TRANSFORM.Math.Examples.check_clamp": {
    "filename": "Math_check_clamp.json",
    "last_updated": "2026-04-07T13:55:46.430781+00:00",
    "n_vars": 1
  },
  "TRANSFORM.Math.Examples.check_cspline": {
    "filename": "Math_check_cspline.json",
    "last_updated": "2026-04-07T13:55:46.433038+00:00",
    "n_vars": 1
  },
  "TRANSFORM.Math.Examples.check_cubicHermiteSpline": {
    "filename": "Math_check_cubicHermiteSpline.json",
    "last_updated": "2026-04-07T13:55:46.435441+00:00",
    "n_vars": 4
  },
  "TRANSFORM.Math.Examples.check_cubicRoots": {
    "filename": "Math_check_cubicRoots.json",
    "last_updated": "2026-04-07T13:55:46.438025+00:00",
    "n_vars": 5
  },
  "TRANSFORM.Math.Examples.check_cumulativeSum": {
    "filename": "Math_check_cumulativeSum.json",
    "last_updated": "2026-04-07T13:55:46.440092+00:00",
    "n_vars": 11
  },
  "TRANSFORM.Math.Examples.check_diff": {
    "filename": "Math_check_diff.json",
    "last_updated": "2026-04-07T13:55:46.442076+00:00",
    "n_vars": 4
  },
  "TRANSFORM.Math.Examples.check_factorial": {
    "filename": "Math_check_factorial.json",
    "last_updated": "2026-04-07T13:55:46.444055+00:00",
    "n_vars": 1
  },
  "TRANSFORM.Math.Examples.check_fillArray": {
    "filename": "Math_check_fillArray.json",
    "last_updated": "2026-04-07T13:55:46.446164+00:00",
    "n_vars": 3
  },
  "TRANSFORM.Math.Examples.check_findPlace": {
    "filename": "Math_check_findPlace.json",
    "last_updated": "2026-04-07T13:55:46.448254+00:00",
    "n_vars": 1
  },
  "TRANSFORM.Math.Examples.check_gamma_Lanczos": {
    "filename": "Math_check_gamma_Lanczos.json",
    "last_updated": "2026-04-07T13:55:46.450372+00:00",
    "n_vars": 10
  },
  "TRANSFORM.Math.Examples.check_indexFilter": {
    "filename": "Math_check_indexFilter.json",
    "last_updated": "2026-04-07T13:55:46.452376+00:00",
    "n_vars": 5
  },
  "TRANSFORM.Math.Examples.check_integral_TrapezoidalRule": {
    "filename": "Math_check_integral_TrapezoidalRule.json",
    "last_updated": "2026-04-07T13:55:46.454293+00:00",
    "n_vars": 1
  },
  "TRANSFORM.Math.Examples.check_interpolate2D": {
    "filename": "Math_check_interpolate2D.json",
    "last_updated": "2026-04-07T13:55:46.456231+00:00",
    "n_vars": 1
  },
  "TRANSFORM.Math.Examples.check_interpolate_wLimit": {
    "filename": "Math_check_interpolate_wLimit.json",
    "last_updated": "2026-04-07T13:55:46.458428+00:00",
    "n_vars": 1
  },
  "TRANSFORM.Math.Examples.check_isMonotonic": {
    "filename": "Math_check_isMonotonic.json",
    "last_updated": "2026-04-07T13:55:46.460629+00:00",
    "n_vars": 4
  },
  "TRANSFORM.Math.Examples.check_linspace_1D": {
    "filename": "Math_check_linspace_1D.json",
    "last_updated": "2026-04-07T13:55:46.462605+00:00",
    "n_vars": 3
  },
  "TRANSFORM.Math.Examples.check_linspace_2D": {
    "filename": "Math_check_linspace_2D.json",
    "last_updated": "2026-04-07T13:55:46.464655+00:00",
    "n_vars": 4
  },
  "TRANSFORM.Math.Examples.check_logspace": {
    "filename": "Math_check_logspace.json",
    "last_updated": "2026-04-07T13:55:46.466807+00:00",
    "n_vars": 10
  },
  "TRANSFORM.Math.Examples.check_max_len_seq": {
    "filename": "Math_check_max_len_seq.json",
    "last_updated": "2026-04-07T13:55:46.469027+00:00",
    "n_vars": 7
  },
  "TRANSFORM.Math.Examples.check_max_len_seq_sine": {
    "filename": "Math_check_max_len_seq_sine.json",
    "last_updated": "2026-04-07T13:55:46.471040+00:00",
    "n_vars": 1
  },
  "TRANSFORM.Math.Examples.check_max_len_seq_sine_time": {
    "filename": "Math_check_max_len_seq_sine_time.json",
    "last_updated": "2026-04-07T13:55:46.473125+00:00",
    "n_vars": 1
  },
  "TRANSFORM.Math.Examples.check_max_len_seq_ternary": {
    "filename": "Math_check_max_len_seq_ternary.json",
    "last_updated": "2026-04-07T13:55:46.475184+00:00",
    "n_vars": 1
  },
  "TRANSFORM.Math.Examples.check_mean": {
    "filename": "Math_check_mean.json",
    "last_updated": "2026-04-07T13:55:46.477194+00:00",
    "n_vars": 1
  },
  "TRANSFORM.Math.Examples.check_meanFactor": {
    "filename": "Math_check_meanFactor.json",
    "last_updated": "2026-04-07T13:55:46.479338+00:00",
    "n_vars": 6
  },
  "TRANSFORM.Math.Examples.check_psi_math": {
    "filename": "Math_check_psi_math.json",
    "last_updated": "2026-04-07T13:55:46.481367+00:00",
    "n_vars": 1
  },
  "TRANSFORM.Math.Examples.check_quadratic": {
    "filename": "Math_check_quadratic.json",
    "last_updated": "2026-04-07T13:55:46.483937+00:00",
    "n_vars": 1
  },
  "TRANSFORM.Math.Examples.check_radialspace": {
    "filename": "Math_check_radialspace.json",
    "last_updated": "2026-04-07T13:55:46.486245+00:00",
    "n_vars": 5
  },
  "TRANSFORM.Math.Examples.check_regFun3": {
    "filename": "Math_check_regFun3.json",
    "last_updated": "2026-04-07T13:55:46.488332+00:00",
    "n_vars": 1
  },
  "TRANSFORM.Math.Examples.check_regRoot": {
    "filename": "Math_check_regRoot.json",
    "last_updated": "2026-04-07T13:55:46.490679+00:00",
    "n_vars": 2
  },
  "TRANSFORM.Math.Examples.check_regStep": {
    "filename": "Math_check_regStep.json",
    "last_updated": "2026-04-07T13:55:46.493075+00:00",
    "n_vars": 2
  },
  "TRANSFORM.Math.Examples.check_replaceArrayValues": {
    "filename": "Math_check_replaceArrayValues.json",
    "last_updated": "2026-04-07T13:55:46.495261+00:00",
    "n_vars": 6
  },
  "TRANSFORM.Math.Examples.check_smoothMax": {
    "filename": "Math_check_smoothMax.json",
    "last_updated": "2026-04-07T13:55:46.497515+00:00",
    "n_vars": 4
  },
  "TRANSFORM.Math.Examples.check_smoothMin": {
    "filename": "Math_check_smoothMin.json",
    "last_updated": "2026-04-07T13:55:46.500228+00:00",
    "n_vars": 4
  },
  "TRANSFORM.Math.Examples.check_spliceCosN": {
    "filename": "Math_check_spliceCosN.json",
    "last_updated": "2026-04-07T13:55:46.502684+00:00",
    "n_vars": 2
  },
  "TRANSFORM.Math.Examples.check_spliceSigmoid": {
    "filename": "Math_check_spliceSigmoid.json",
    "last_updated": "2026-04-07T13:55:46.505055+00:00",
    "n_vars": 3
  },
  "TRANSFORM.Math.Examples.check_spliceTanh": {
    "filename": "Math_check_spliceTanh.json",
    "last_updated": "2026-04-07T13:55:46.507467+00:00",
    "n_vars": 2
  },
  "TRANSFORM.Math.Examples.check_variableFactor": {
    "filename": "Math_check_variableFactor.json",
    "last_updated": "2026-04-07T13:55:46.509722+00:00",
    "n_vars": 6
  },
  "TRANSFORM.Math.Examples.check_xor": {
    "filename": "Math_check_xor.json",
    "last_updated": "2026-04-07T13:55:46.511702+00:00",
    "n_vars": 5
  },
  "TRANSFORM.Media.Fluids.Examples.IncompressibleLithium": {
    "filename": "Media_Fluids_IncompressibleLithium.json",
    "last_updated": "2026-04-07T13:55:46.517797+00:00",
    "n_vars": 6
  },
  "TRANSFORM.Media.Fluids.Examples.LinearDOWTHERM_A_95C_pT": {
    "filename": "Media_Fluids_LinearDOWTHERM_A_95C_pT.json",
    "last_updated": "2026-04-07T13:55:46.520117+00:00",
    "n_vars": 3
  },
  "TRANSFORM.Media.Fluids.Examples.LinearEthyleneGlycol_50_Water": {
    "filename": "Media_Fluids_LinearEthyleneGlycol_50_Water.json",
    "last_updated": "2026-04-07T13:55:46.522190+00:00",
    "n_vars": 3
  },
  "TRANSFORM.Media.Fluids.Examples.LinearFLiBe_12Th_05U_pT": {
    "filename": "Media_Fluids_LinearFLiBe_12Th_05U_pT.json",
    "last_updated": "2026-04-07T13:55:46.524190+00:00",
    "n_vars": 3
  },
  "TRANSFORM.Media.Fluids.Examples.LinearFLiBe_64LiF_30BeF2_5ZrF4_1UF4_CrFeNi": {
    "filename": "Media_Fluids_LinearFLiBe_64LiF_30BeF2_5ZrF4_1UF4_CrFeNi.json",
    "last_updated": "2026-04-07T13:55:46.526203+00:00",
    "n_vars": 3
  },
  "TRANSFORM.Media.Fluids.Examples.LinearFLiBe_9999Li7": {
    "filename": "Media_Fluids_LinearFLiBe_9999Li7.json",
    "last_updated": "2026-04-07T13:55:46.528154+00:00",
    "n_vars": 3
  },
  "TRANSFORM.Media.Fluids.Examples.LinearFLiBe_pT": {
    "filename": "Media_Fluids_LinearFLiBe_pT.json",
    "last_updated": "2026-04-07T13:55:46.530214+00:00",
    "n_vars": 9
  },
  "TRANSFORM.Media.Fluids.Examples.LinearKClMGCl2_67_33_pT": {
    "filename": "Media_Fluids_LinearKClMGCl2_67_33_pT.json",
    "last_updated": "2026-04-07T13:55:46.532237+00:00",
    "n_vars": 3
  },
  "TRANSFORM.Media.Fluids.Examples.LinearNaClKClMgCl2_30_20_50_pT": {
    "filename": "Media_Fluids_LinearNaClKClMgCl2_30_20_50_pT.json",
    "last_updated": "2026-04-07T13:55:46.534293+00:00",
    "n_vars": 3
  },
  "TRANSFORM.Media.Fluids.Examples.LinearNaK_22_78": {
    "filename": "Media_Fluids_LinearNaK_22_78.json",
    "last_updated": "2026-04-07T13:55:46.536294+00:00",
    "n_vars": 3
  },
  "TRANSFORM.Media.Fluids.Examples.LinearTherminol66_A_250C": {
    "filename": "Media_Fluids_LinearTherminol66_A_250C.json",
    "last_updated": "2026-04-07T13:55:46.538343+00:00",
    "n_vars": 3
  },
  "TRANSFORM.Media.Fluids.Examples.LinearWaterHot_pT": {
    "filename": "Media_Fluids_LinearWaterHot_pT.json",
    "last_updated": "2026-04-07T13:55:46.540400+00:00",
    "n_vars": 3
  },
  "TRANSFORM.Media.Fluids.Examples.TableBasedTherminol66": {
    "filename": "Media_Fluids_TableBasedTherminol66.json",
    "last_updated": "2026-04-07T13:55:46.542500+00:00",
    "n_vars": 3
  },
  "TRANSFORM.Media.IdealGases.Examples.HeXe": {
    "filename": "Media_IdealGases_HeXe.json",
    "last_updated": "2026-04-07T13:55:46.544541+00:00",
    "n_vars": 9
  },
  "TRANSFORM.Media.IdealGases.Examples.HeXeAlternate": {
    "filename": "Media_IdealGases_HeXeAlternate.json",
    "last_updated": "2026-04-07T13:55:46.546540+00:00",
    "n_vars": 9
  },
  "TRANSFORM.Media.Solids.Examples.Hastelloy_N_Haynes": {
    "filename": "Media_Solids_Hastelloy_N_Haynes.json",
    "last_updated": "2026-04-07T13:55:46.548769+00:00",
    "n_vars": 6
  },
  "TRANSFORM.Media.Solids.Examples.Inconel690": {
    "filename": "Media_Solids_Inconel690.json",
    "last_updated": "2026-04-07T13:55:46.550753+00:00",
    "n_vars": 6
  },
  "TRANSFORM.Media.Solids.Examples.Molybdenum": {
    "filename": "Media_Solids_Molybdenum.json",
    "last_updated": "2026-04-07T13:55:46.552869+00:00",
    "n_vars": 6
  },
  "TRANSFORM.Media.Solids.Examples.Tungsten": {
    "filename": "Media_Solids_Tungsten.json",
    "last_updated": "2026-04-07T13:55:46.554830+00:00",
    "n_vars": 6
  },
  "TRANSFORM.Media.Solids.Examples.UC": {
    "filename": "Media_Solids_UC.json",
    "last_updated": "2026-04-07T13:55:46.556863+00:00",
    "n_vars": 6
  },
  "TRANSFORM.Media.Solids.Examples.UO2": {
    "filename": "Media_Solids_UO2.json",
    "last_updated": "2026-04-07T13:55:46.559041+00:00",
    "n_vars": 6
  },
  "TRANSFORM.Nuclear.CoreSubchannels.Examples.Regions.3.Test": {
    "filename": "Nuclear_CoreSubchannels_Regions_3_Test.json",
    "last_updated": "2026-04-07T13:55:46.561670+00:00",
    "n_vars": 1
  },
  "TRANSFORM.Nuclear.ReactorKinetics.Examples.Functions.Initial_powerBased_powerHistory": {
    "filename": "Nuclear_RK_Fn_Initial_powerBased_powerHistory.json",
    "last_updated": "2026-04-07T13:55:46.564673+00:00",
    "n_vars": 17
  },
  "TRANSFORM.Nuclear.ReactorKinetics.Examples.PointKinetics_Drift_Test_feedback_Xenon": {
    "filename": "Nuclear_RK_PointKinetics_Drift_Test_feedback_Xenon.json",
    "last_updated": "2026-04-07T13:55:46.568485+00:00",
    "n_vars": 3
  },
  "TRANSFORM.Nuclear.ReactorKinetics.Examples.PointKinetics_Drift_Test_flat": {
    "filename": "Nuclear_RK_PointKinetics_Drift_Test_flat.json",
    "last_updated": "2026-04-07T13:55:46.571149+00:00",
    "n_vars": 3
  },
  "TRANSFORM.Nuclear.ReactorKinetics.Examples.PointKinetics_Drift_Test_flat_Xenon": {
    "filename": "Nuclear_RK_PointKinetics_Drift_Test_flat_Xenon.json",
    "last_updated": "2026-04-07T13:55:46.573646+00:00",
    "n_vars": 3
  },
  "TRANSFORM.Nuclear.ReactorKinetics.Examples.PointKinetics_Drift_Test_sine": {
    "filename": "Nuclear_RK_PointKinetics_Drift_Test_sine.json",
    "last_updated": "2026-04-07T13:55:46.576118+00:00",
    "n_vars": 3
  },
  "TRANSFORM.Nuclear.ReactorKinetics.Examples.PointKinetics_Test": {
    "filename": "Nuclear_RK_PointKinetics_Test.json",
    "last_updated": "2026-04-07T13:55:46.578453+00:00",
    "n_vars": 1
  },
  "TRANSFORM.Nuclear.ReactorKinetics.Examples.PointKinetics_vs_ApproximateOneGroup": {
    "filename": "Nuclear_RK_PointKinetics_vs_ApproximateOneGroup.json",
    "last_updated": "2026-04-07T13:55:46.580824+00:00",
    "n_vars": 1
  },
  "TRANSFORM.Nuclear.ReactorKinetics.Examples.Reactivity.FissionProducts_Test": {
    "filename": "Nuclear_RK_Reactivity_FissionProducts_Test.json",
    "last_updated": "2026-04-07T13:55:46.583247+00:00",
    "n_vars": 3
  },
  "TRANSFORM.Units.Conversions.Functions.Activity_Bq.Examples.check_Bq": {
    "filename": "Units_Conversions_Functions_Activity_Bq_check_Bq.json",
    "last_updated": "2026-04-07T13:55:46.585657+00:00",
    "n_vars": 2
  },
  "TRANSFORM.Units.Conversions.Functions.Activity_Bq.Examples.check_Ci": {
    "filename": "Units_Conversions_Functions_Activity_Bq_check_Ci.json",
    "last_updated": "2026-04-07T13:55:46.587672+00:00",
    "n_vars": 2
  },
  "TRANSFORM.Units.Conversions.Functions.Angle_rad.Examples.check_rad": {
    "filename": "Units_Conversions_Functions_Angle_rad_check_rad.json",
    "last_updated": "2026-04-07T13:55:46.589844+00:00",
    "n_vars": 2
  },
  "TRANSFORM.Units.Conversions.Functions.AngularVelocity_rad_s.Examples.check_rad_s": {
    "filename": "Units_Conversions_Functions_AngularVelocity_rad_s_check_rad_s.json",
    "last_updated": "2026-04-07T13:55:46.591934+00:00",
    "n_vars": 2
  },
  "TRANSFORM.Units.Conversions.Functions.Area_m2.Examples.check_barn": {
    "filename": "Units_Conversions_Functions_Area_m2_check_barn.json",
    "last_updated": "2026-04-07T13:55:46.593889+00:00",
    "n_vars": 2
  },
  "TRANSFORM.Units.Conversions.Functions.Area_m2.Examples.check_ft2": {
    "filename": "Units_Conversions_Functions_Area_m2_check_ft2.json",
    "last_updated": "2026-04-07T13:55:46.596048+00:00",
    "n_vars": 2
  },
  "TRANSFORM.Units.Conversions.Functions.Area_m2.Examples.check_in2": {
    "filename": "Units_Conversions_Functions_Area_m2_check_in2.json",
    "last_updated": "2026-04-07T13:55:46.598110+00:00",
    "n_vars": 2
  },
  "TRANSFORM.Units.Conversions.Functions.Area_m2.Examples.check_m2": {
    "filename": "Units_Conversions_Functions_Area_m2_check_m2.json",
    "last_updated": "2026-04-07T13:55:46.600212+00:00",
    "n_vars": 2
  },
  "TRANSFORM.Units.Conversions.Functions.CoefficientOfHeatTransfer_W_m2K.Examples.check_W_m2K": {
    "filename": "Units_Conversions_Functions_CoefficientOfHeatTransfer_W_m2K_check_W_m2K.json",
    "last_updated": "2026-04-07T13:55:46.604206+00:00",
    "n_vars": 2
  },
  "TRANSFORM.Units.Conversions.Functions.CoefficientOfHeatTransfer_W_m2K.Examples.check_btu_hrft2degF": {
    "filename": "Units_Conversions_Functions_CoefficientOfHeatTransfer_W_m2K_check_btu_hrft2degF.json",
    "last_updated": "2026-04-07T13:55:46.602207+00:00",
    "n_vars": 2
  },
  "TRANSFORM.Units.Conversions.Functions.Concentration_mol_m3.Examples.check_mol_L": {
    "filename": "Units_Conversions_Functions_Concentration_mol_m3_check_mol_L.json",
    "last_updated": "2026-04-07T13:55:46.606232+00:00",
    "n_vars": 2
  },
  "TRANSFORM.Units.Conversions.Functions.Concentration_mol_m3.Examples.check_mol_m3": {
    "filename": "Units_Conversions_Functions_Concentration_mol_m3_check_mol_m3.json",
    "last_updated": "2026-04-07T13:55:46.608283+00:00",
    "n_vars": 2
  },
  "TRANSFORM.Units.Conversions.Functions.Density_kg_m3.Examples.check_g_cm3": {
    "filename": "Units_Conversions_Functions_Density_kg_m3_check_g_cm3.json",
    "last_updated": "2026-04-07T13:55:46.610380+00:00",
    "n_vars": 2
  },
  "TRANSFORM.Units.Conversions.Functions.Density_kg_m3.Examples.check_kg_m3": {
    "filename": "Units_Conversions_Functions_Density_kg_m3_check_kg_m3.json",
    "last_updated": "2026-04-07T13:55:46.612374+00:00",
    "n_vars": 2
  },
  "TRANSFORM.Units.Conversions.Functions.Density_kg_m3.Examples.check_lb_ft3": {
    "filename": "Units_Conversions_Functions_Density_kg_m3_check_lb_ft3.json",
    "last_updated": "2026-04-07T13:55:46.614367+00:00",
    "n_vars": 2
  },
  "TRANSFORM.Units.Conversions.Functions.Distance_m.Examples.check_cm": {
    "filename": "Units_Conversions_Functions_Distance_m_check_cm.json",
    "last_updated": "2026-04-07T13:55:46.616367+00:00",
    "n_vars": 2
  },
  "TRANSFORM.Units.Conversions.Functions.Distance_m.Examples.check_ft": {
    "filename": "Units_Conversions_Functions_Distance_m_check_ft.json",
    "last_updated": "2026-04-07T13:55:46.618338+00:00",
    "n_vars": 2
  },
  "TRANSFORM.Units.Conversions.Functions.Distance_m.Examples.check_in": {
    "filename": "Units_Conversions_Functions_Distance_m_check_in.json",
    "last_updated": "2026-04-07T13:55:46.620424+00:00",
    "n_vars": 2
  },
  "TRANSFORM.Units.Conversions.Functions.Distance_m.Examples.check_m": {
    "filename": "Units_Conversions_Functions_Distance_m_check_m.json",
    "last_updated": "2026-04-07T13:55:46.622404+00:00",
    "n_vars": 2
  },
  "TRANSFORM.Units.Conversions.Functions.Distance_m.Examples.check_micron": {
    "filename": "Units_Conversions_Functions_Distance_m_check_micron.json",
    "last_updated": "2026-04-07T13:55:46.624593+00:00",
    "n_vars": 2
  },
  "TRANSFORM.Units.Conversions.Functions.Distance_m.Examples.check_mm": {
    "filename": "Units_Conversions_Functions_Distance_m_check_mm.json",
    "last_updated": "2026-04-07T13:55:46.626664+00:00",
    "n_vars": 2
  },
  "TRANSFORM.Units.Conversions.Functions.DynamicViscosity_kg_ms.Examples.check_kg_ms": {
    "filename": "Units_Conversions_Functions_DynamicViscosity_kg_ms_check_kg_ms.json",
    "last_updated": "2026-04-07T13:55:46.628718+00:00",
    "n_vars": 2
  },
  "TRANSFORM.Units.Conversions.Functions.DynamicViscosity_kg_ms.Examples.check_lb_hrft": {
    "filename": "Units_Conversions_Functions_DynamicViscosity_kg_ms_check_lb_hrft.json",
    "last_updated": "2026-04-07T13:55:46.630746+00:00",
    "n_vars": 2
  },
  "TRANSFORM.Units.Conversions.Functions.Energy_J.Examples.check_J": {
    "filename": "Units_Conversions_Functions_Energy_J_check_J.json",
    "last_updated": "2026-04-07T13:55:46.634765+00:00",
    "n_vars": 2
  },
  "TRANSFORM.Units.Conversions.Functions.Energy_J.Examples.check_MeV": {
    "filename": "Units_Conversions_Functions_Energy_J_check_MeV.json",
    "last_updated": "2026-04-07T13:55:46.636809+00:00",
    "n_vars": 2
  },
  "TRANSFORM.Units.Conversions.Functions.Energy_J.Examples.check_btu": {
    "filename": "Units_Conversions_Functions_Energy_J_check_btu.json",
    "last_updated": "2026-04-07T13:55:46.632752+00:00",
    "n_vars": 2
  },
  "TRANSFORM.Units.Conversions.Functions.Force_N.Examples.check_N": {
    "filename": "Units_Conversions_Functions_Force_N_check_N.json",
    "last_updated": "2026-04-07T13:55:46.640845+00:00",
    "n_vars": 2
  },
  "TRANSFORM.Units.Conversions.Functions.Force_N.Examples.check_lbf": {
    "filename": "Units_Conversions_Functions_Force_N_check_lbf.json",
    "last_updated": "2026-04-07T13:55:46.638901+00:00",
    "n_vars": 2
  },
  "TRANSFORM.Units.Conversions.Functions.Frequency_Hz.Examples.check_Hz": {
    "filename": "Units_Conversions_Functions_Frequency_Hz_check_Hz.json",
    "last_updated": "2026-04-07T13:55:46.642869+00:00",
    "n_vars": 2
  },
  "TRANSFORM.Units.Conversions.Functions.MassFlowRate_kg_s.Examples.check_kg_s": {
    "filename": "Units_Conversions_Functions_MassFlowRate_kg_s_check_kg_s.json",
    "last_updated": "2026-04-07T13:55:46.649264+00:00",
    "n_vars": 2
  },
  "TRANSFORM.Units.Conversions.Functions.MassFlowRate_kg_s.Examples.check_lbm_hr": {
    "filename": "Units_Conversions_Functions_MassFlowRate_kg_s_check_lbm_hr.json",
    "last_updated": "2026-04-07T13:55:46.651365+00:00",
    "n_vars": 2
  },
  "TRANSFORM.Units.Conversions.Functions.MassFlowRate_kg_s.Examples.check_lbm_min": {
    "filename": "Units_Conversions_Functions_MassFlowRate_kg_s_check_lbm_min.json",
    "last_updated": "2026-04-07T13:55:46.653425+00:00",
    "n_vars": 2
  },
  "TRANSFORM.Units.Conversions.Functions.MassFlowRate_kg_s.Examples.check_lbm_s": {
    "filename": "Units_Conversions_Functions_MassFlowRate_kg_s_check_lbm_s.json",
    "last_updated": "2026-04-07T13:55:46.655700+00:00",
    "n_vars": 2
  },
  "TRANSFORM.Units.Conversions.Functions.Mass_kg.Examples.check_kg": {
    "filename": "Units_Conversions_Functions_Mass_kg_check_kg.json",
    "last_updated": "2026-04-07T13:55:46.645050+00:00",
    "n_vars": 2
  },
  "TRANSFORM.Units.Conversions.Functions.Mass_kg.Examples.check_lbm": {
    "filename": "Units_Conversions_Functions_Mass_kg_check_lbm.json",
    "last_updated": "2026-04-07T13:55:46.647114+00:00",
    "n_vars": 2
  },
  "TRANSFORM.Units.Conversions.Functions.Power_W.Examples.check_W": {
    "filename": "Units_Conversions_Functions_Power_W_check_W.json",
    "last_updated": "2026-04-07T13:55:46.662021+00:00",
    "n_vars": 2
  },
  "TRANSFORM.Units.Conversions.Functions.Power_W.Examples.check_btu_hr": {
    "filename": "Units_Conversions_Functions_Power_W_check_btu_hr.json",
    "last_updated": "2026-04-07T13:55:46.657804+00:00",
    "n_vars": 2
  },
  "TRANSFORM.Units.Conversions.Functions.Power_W.Examples.check_hp": {
    "filename": "Units_Conversions_Functions_Power_W_check_hp.json",
    "last_updated": "2026-04-07T13:55:46.659866+00:00",
    "n_vars": 2
  },
  "TRANSFORM.Units.Conversions.Functions.PrefixMultipliers.Examples.check_atto": {
    "filename": "Units_Conversions_Functions_PrefixMultipliers_check_atto.json",
    "last_updated": "2026-04-07T13:55:46.664165+00:00",
    "n_vars": 2
  },
  "TRANSFORM.Units.Conversions.Functions.PrefixMultipliers.Examples.check_centi": {
    "filename": "Units_Conversions_Functions_PrefixMultipliers_check_centi.json",
    "last_updated": "2026-04-07T13:55:46.666237+00:00",
    "n_vars": 2
  },
  "TRANSFORM.Units.Conversions.Functions.PrefixMultipliers.Examples.check_deci": {
    "filename": "Units_Conversions_Functions_PrefixMultipliers_check_deci.json",
    "last_updated": "2026-04-07T13:55:46.668404+00:00",
    "n_vars": 2
  },
  "TRANSFORM.Units.Conversions.Functions.PrefixMultipliers.Examples.check_deka": {
    "filename": "Units_Conversions_Functions_PrefixMultipliers_check_deka.json",
    "last_updated": "2026-04-07T13:55:46.670584+00:00",
    "n_vars": 2
  },
  "TRANSFORM.Units.Conversions.Functions.PrefixMultipliers.Examples.check_exa": {
    "filename": "Units_Conversions_Functions_PrefixMultipliers_check_exa.json",
    "last_updated": "2026-04-07T13:55:46.672634+00:00",
    "n_vars": 2
  },
  "TRANSFORM.Units.Conversions.Functions.PrefixMultipliers.Examples.check_femto": {
    "filename": "Units_Conversions_Functions_PrefixMultipliers_check_femto.json",
    "last_updated": "2026-04-07T13:55:46.674779+00:00",
    "n_vars": 2
  },
  "TRANSFORM.Units.Conversions.Functions.PrefixMultipliers.Examples.check_giga": {
    "filename": "Units_Conversions_Functions_PrefixMultipliers_check_giga.json",
    "last_updated": "2026-04-07T13:55:46.677021+00:00",
    "n_vars": 2
  },
  "TRANSFORM.Units.Conversions.Functions.PrefixMultipliers.Examples.check_hecto": {
    "filename": "Units_Conversions_Functions_PrefixMultipliers_check_hecto.json",
    "last_updated": "2026-04-07T13:55:46.679288+00:00",
    "n_vars": 2
  },
  "TRANSFORM.Units.Conversions.Functions.PrefixMultipliers.Examples.check_kilo": {
    "filename": "Units_Conversions_Functions_PrefixMultipliers_check_kilo.json",
    "last_updated": "2026-04-07T13:55:46.681552+00:00",
    "n_vars": 2
  },
  "TRANSFORM.Units.Conversions.Functions.PrefixMultipliers.Examples.check_mega": {
    "filename": "Units_Conversions_Functions_PrefixMultipliers_check_mega.json",
    "last_updated": "2026-04-07T13:55:46.683525+00:00",
    "n_vars": 2
  },
  "TRANSFORM.Units.Conversions.Functions.PrefixMultipliers.Examples.check_micro": {
    "filename": "Units_Conversions_Functions_PrefixMultipliers_check_micro.json",
    "last_updated": "2026-04-07T13:55:46.685646+00:00",
    "n_vars": 2
  },
  "TRANSFORM.Units.Conversions.Functions.PrefixMultipliers.Examples.check_milli": {
    "filename": "Units_Conversions_Functions_PrefixMultipliers_check_milli.json",
    "last_updated": "2026-04-07T13:55:46.687693+00:00",
    "n_vars": 2
  },
  "TRANSFORM.Units.Conversions.Functions.PrefixMultipliers.Examples.check_nano": {
    "filename": "Units_Conversions_Functions_PrefixMultipliers_check_nano.json",
    "last_updated": "2026-04-07T13:55:46.689808+00:00",
    "n_vars": 2
  },
  "TRANSFORM.Units.Conversions.Functions.PrefixMultipliers.Examples.check_none": {
    "filename": "Units_Conversions_Functions_PrefixMultipliers_check_none.json",
    "last_updated": "2026-04-07T13:55:46.691852+00:00",
    "n_vars": 2
  },
  "TRANSFORM.Units.Conversions.Functions.PrefixMultipliers.Examples.check_peta": {
    "filename": "Units_Conversions_Functions_PrefixMultipliers_check_peta.json",
    "last_updated": "2026-04-07T13:55:46.693862+00:00",
    "n_vars": 2
  },
  "TRANSFORM.Units.Conversions.Functions.PrefixMultipliers.Examples.check_pico": {
    "filename": "Units_Conversions_Functions_PrefixMultipliers_check_pico.json",
    "last_updated": "2026-04-07T13:55:46.696043+00:00",
    "n_vars": 2
  },
  "TRANSFORM.Units.Conversions.Functions.PrefixMultipliers.Examples.check_tera": {
    "filename": "Units_Conversions_Functions_PrefixMultipliers_check_tera.json",
    "last_updated": "2026-04-07T13:55:46.698106+00:00",
    "n_vars": 2
  },
  "TRANSFORM.Units.Conversions.Functions.PrefixMultipliers.Examples.check_yocto": {
    "filename": "Units_Conversions_Functions_PrefixMultipliers_check_yocto.json",
    "last_updated": "2026-04-07T13:55:46.700293+00:00",
    "n_vars": 2
  },
  "TRANSFORM.Units.Conversions.Functions.PrefixMultipliers.Examples.check_yotta": {
    "filename": "Units_Conversions_Functions_PrefixMultipliers_check_yotta.json",
    "last_updated": "2026-04-07T13:55:46.702356+00:00",
    "n_vars": 2
  },
  "TRANSFORM.Units.Conversions.Functions.PrefixMultipliers.Examples.check_zepto": {
    "filename": "Units_Conversions_Functions_PrefixMultipliers_check_zepto.json",
    "last_updated": "2026-04-07T13:55:46.704660+00:00",
    "n_vars": 2
  },
  "TRANSFORM.Units.Conversions.Functions.PrefixMultipliers.Examples.check_zetta": {
    "filename": "Units_Conversions_Functions_PrefixMultipliers_check_zetta.json",
    "last_updated": "2026-04-07T13:55:46.706821+00:00",
    "n_vars": 2
  },
  "TRANSFORM.Units.Conversions.Functions.Pressure_Pa.Examples.check_MPa": {
    "filename": "Units_Conversions_Functions_Pressure_Pa_check_MPa.json",
    "last_updated": "2026-04-07T13:55:46.719317+00:00",
    "n_vars": 2
  },
  "TRANSFORM.Units.Conversions.Functions.Pressure_Pa.Examples.check_Pa": {
    "filename": "Units_Conversions_Functions_Pressure_Pa_check_Pa.json",
    "last_updated": "2026-04-07T13:55:46.721498+00:00",
    "n_vars": 2
  },
  "TRANSFORM.Units.Conversions.Functions.Pressure_Pa.Examples.check_atm": {
    "filename": "Units_Conversions_Functions_Pressure_Pa_check_atm.json",
    "last_updated": "2026-04-07T13:55:46.708967+00:00",
    "n_vars": 2
  },
  "TRANSFORM.Units.Conversions.Functions.Pressure_Pa.Examples.check_bar": {
    "filename": "Units_Conversions_Functions_Pressure_Pa_check_bar.json",
    "last_updated": "2026-04-07T13:55:46.711009+00:00",
    "n_vars": 2
  },
  "TRANSFORM.Units.Conversions.Functions.Pressure_Pa.Examples.check_inHg": {
    "filename": "Units_Conversions_Functions_Pressure_Pa_check_inHg.json",
    "last_updated": "2026-04-07T13:55:46.713117+00:00",
    "n_vars": 2
  },
  "TRANSFORM.Units.Conversions.Functions.Pressure_Pa.Examples.check_kPa": {
    "filename": "Units_Conversions_Functions_Pressure_Pa_check_kPa.json",
    "last_updated": "2026-04-07T13:55:46.715180+00:00",
    "n_vars": 2
  },
  "TRANSFORM.Units.Conversions.Functions.Pressure_Pa.Examples.check_mH2O_psi": {
    "filename": "Units_Conversions_Functions_Pressure_Pa_check_mH2O_psi.json",
    "last_updated": "2026-04-07T13:55:46.717250+00:00",
    "n_vars": 2
  },
  "TRANSFORM.Units.Conversions.Functions.Pressure_Pa.Examples.check_psi": {
    "filename": "Units_Conversions_Functions_Pressure_Pa_check_psi.json",
    "last_updated": "2026-04-07T13:55:46.723650+00:00",
    "n_vars": 2
  },
  "TRANSFORM.Units.Conversions.Functions.SpecificEnergy_J_kg.Examples.check_J_kg": {
    "filename": "Units_Conversions_Functions_SpecificEnergy_J_kg_check_J_kg.json",
    "last_updated": "2026-04-07T13:55:46.725807+00:00",
    "n_vars": 2
  },
  "TRANSFORM.Units.Conversions.Functions.SpecificHeatAndEntropy_J_kgK.Examples.check_J_kgK": {
    "filename": "Units_Conversions_Functions_SpecificHeatAndEntropy_J_kgK_check_J_kgK.json",
    "last_updated": "2026-04-07T13:55:46.730215+00:00",
    "n_vars": 2
  },
  "TRANSFORM.Units.Conversions.Functions.SpecificHeatAndEntropy_J_kgK.Examples.check_btu_lbdegF": {
    "filename": "Units_Conversions_Functions_SpecificHeatAndEntropy_J_kgK_check_btu_lbdegF.json",
    "last_updated": "2026-04-07T13:55:46.728046+00:00",
    "n_vars": 2
  },
  "TRANSFORM.Units.Conversions.Functions.TemperatureDifference_dK.Examples.check_degCorK_diff": {
    "filename": "Units_Conversions_Functions_TemperatureDifference_dK_check_degCorK_diff.json",
    "last_updated": "2026-04-07T13:55:46.740789+00:00",
    "n_vars": 2
  },
  "TRANSFORM.Units.Conversions.Functions.TemperatureDifference_dK.Examples.check_degForR_diff": {
    "filename": "Units_Conversions_Functions_TemperatureDifference_dK_check_degForR_diff.json",
    "last_updated": "2026-04-07T13:55:46.742927+00:00",
    "n_vars": 2
  },
  "TRANSFORM.Units.Conversions.Functions.Temperature_K.Examples.check_K": {
    "filename": "Units_Conversions_Functions_Temperature_K_check_K.json",
    "last_updated": "2026-04-07T13:55:46.738743+00:00",
    "n_vars": 2
  },
  "TRANSFORM.Units.Conversions.Functions.Temperature_K.Examples.check_degC": {
    "filename": "Units_Conversions_Functions_Temperature_K_check_degC.json",
    "last_updated": "2026-04-07T13:55:46.732409+00:00",
    "n_vars": 2
  },
  "TRANSFORM.Units.Conversions.Functions.Temperature_K.Examples.check_degF": {
    "filename": "Units_Conversions_Functions_Temperature_K_check_degF.json",
    "last_updated": "2026-04-07T13:55:46.734455+00:00",
    "n_vars": 2
  },
  "TRANSFORM.Units.Conversions.Functions.Temperature_K.Examples.check_degR": {
    "filename": "Units_Conversions_Functions_Temperature_K_check_degR.json",
    "last_updated": "2026-04-07T13:55:46.736622+00:00",
    "n_vars": 2
  },
  "TRANSFORM.Units.Conversions.Functions.ThermalConductivity_W_mK.Examples.check_W_mK": {
    "filename": "Units_Conversions_Functions_ThermalConductivity_W_mK_check_W_mK.json",
    "last_updated": "2026-04-07T13:55:46.747377+00:00",
    "n_vars": 2
  },
  "TRANSFORM.Units.Conversions.Functions.ThermalConductivity_W_mK.Examples.check_btu_hrftdegF": {
    "filename": "Units_Conversions_Functions_ThermalConductivity_W_mK_check_btu_hrftdegF.json",
    "last_updated": "2026-04-07T13:55:46.745133+00:00",
    "n_vars": 2
  },
  "TRANSFORM.Units.Conversions.Functions.Time_s.Examples.check_day": {
    "filename": "Units_Conversions_Functions_Time_s_check_day.json",
    "last_updated": "2026-04-07T13:55:46.749696+00:00",
    "n_vars": 2
  },
  "TRANSFORM.Units.Conversions.Functions.Time_s.Examples.check_hr": {
    "filename": "Units_Conversions_Functions_Time_s_check_hr.json",
    "last_updated": "2026-04-07T13:55:46.751824+00:00",
    "n_vars": 2
  },
  "TRANSFORM.Units.Conversions.Functions.Time_s.Examples.check_min": {
    "filename": "Units_Conversions_Functions_Time_s_check_min.json",
    "last_updated": "2026-04-07T13:55:46.753830+00:00",
    "n_vars": 2
  },
  "TRANSFORM.Units.Conversions.Functions.Time_s.Examples.check_s": {
    "filename": "Units_Conversions_Functions_Time_s_check_s.json",
    "last_updated": "2026-04-07T13:55:46.755906+00:00",
    "n_vars": 2
  },
  "TRANSFORM.Units.Conversions.Functions.Time_s.Examples.check_yr": {
    "filename": "Units_Conversions_Functions_Time_s_check_yr.json",
    "last_updated": "2026-04-07T13:55:46.758036+00:00",
    "n_vars": 2
  },
  "TRANSFORM.Units.Conversions.Functions.Velocity_m_s.Examples.check_ft_s": {
    "filename": "Units_Conversions_Functions_Velocity_m_s_check_ft_s.json",
    "last_updated": "2026-04-07T13:55:46.760225+00:00",
    "n_vars": 2
  },
  "TRANSFORM.Units.Conversions.Functions.Velocity_m_s.Examples.check_m_s": {
    "filename": "Units_Conversions_Functions_Velocity_m_s_check_m_s.json",
    "last_updated": "2026-04-07T13:55:46.762479+00:00",
    "n_vars": 2
  },
  "TRANSFORM.Units.Conversions.Functions.VolumeFlowRate_m3_s.Examples.check_gpm": {
    "filename": "Units_Conversions_Functions_VolumeFlowRate_m3_s_check_gpm.json",
    "last_updated": "2026-04-07T13:55:46.769251+00:00",
    "n_vars": 2
  },
  "TRANSFORM.Units.Conversions.Functions.VolumeFlowRate_m3_s.Examples.check_m3_s": {
    "filename": "Units_Conversions_Functions_VolumeFlowRate_m3_s_check_m3_s.json",
    "last_updated": "2026-04-07T13:55:46.771309+00:00",
    "n_vars": 2
  },
  "TRANSFORM.Units.Conversions.Functions.Volume_m3.Examples.check_ft3": {
    "filename": "Units_Conversions_Functions_Volume_m3_check_ft3.json",
    "last_updated": "2026-04-07T13:55:46.764768+00:00",
    "n_vars": 2
  },
  "TRANSFORM.Units.Conversions.Functions.Volume_m3.Examples.check_m3": {
    "filename": "Units_Conversions_Functions_Volume_m3_check_m3.json",
    "last_updated": "2026-04-07T13:55:46.767099+00:00",
    "n_vars": 2
  },
  "TRANSFORM.Units.Conversions.Models.Examples.check_Conversion": {
    "filename": "Units_Conversions_Models_check_Conversion.json",
    "last_updated": "2026-04-07T13:55:46.773362+00:00",
    "n_vars": 2
  },
  "TRANSFORM.Utilities.Diagnostics.Examples.CheckEquality": {
    "filename": "Utilities_Diagnostics_CheckEquality.json",
    "last_updated": "2026-04-07T13:55:46.775801+00:00",
    "n_vars": 1
  },
  "TRANSFORM.Utilities.Visualizers.PlotMap.Examples.PlotMap_2_points_withTrace_Test": {
    "filename": "Utilities_Visualizers_PlotMap_PlotMap_2_points_withTrace_Test.json",
    "last_updated": "2026-04-07T13:55:46.778258+00:00",
    "n_vars": 1
  },
  "TRANSFORM.Utilities.Visualizers.PlotMap.Examples.PlotMap_2points_Test": {
    "filename": "Utilities_Visualizers_PlotMap_PlotMap_2points_Test.json",
    "last_updated": "2026-04-07T13:55:46.780587+00:00",
    "n_vars": 2
  },
  "TRANSFORM.Utilities.Visualizers.PlotMap.Examples.PlotMap_Test": {
    "filename": "Utilities_Visualizers_PlotMap_PlotMap_Test.json",
    "last_updated": "2026-04-07T13:55:46.783264+00:00",
    "n_vars": 2
  },
  "TRANSFORM.Utilities.Visualizers.PlotMap.Examples.PlotMap_withTrace_Test": {
    "filename": "Utilities_Visualizers_PlotMap_PlotMap_withTrace_Test.json",
    "last_updated": "2026-04-07T13:55:46.785686+00:00",
    "n_vars": 1
  }
}
